[{"symbol": "sz301377", "train_return": 0.008441438187245413, "val_return": 0.007045122716919103, "test_return": 0.06738172472596132, "train_count": 47, "val_count": 65, "test_count": 49, "train_win_rate": 0.574468085106383, "val_win_rate": 0.5538461538461539, "test_win_rate": 0.6938775510204082, "roe": 10.75, "revenue_growth": 29.13, "profit_growth": 63.94, "gross_margin": 40.62, "debt_ratio": 34.45}, {"symbol": "sz000815", "train_return": 0.011484164997877359, "val_return": 0.020576042816170686, "test_return": 0.062297823897987784, "train_count": 101, "val_count": 48, "test_count": 30, "train_win_rate": 0.43564356435643564, "val_win_rate": 0.5208333333333334, "test_win_rate": 0.6333333333333333, "roe": 2.42, "revenue_growth": -63.03, "profit_growth": 425.35, "gross_margin": 40.84, "debt_ratio": 40.3}, {"symbol": "sz001309", "train_return": 0.02236980975737968, "val_return": 0.013871878691970995, "test_return": 0.06146899902831452, "train_count": 62, "val_count": 42, "test_count": 37, "train_win_rate": 0.5645161290322581, "val_win_rate": 0.5238095238095238, "test_win_rate": 0.6486486486486487, "roe": 24.21, "revenue_growth": 126.07, "profit_growth": 96.35, "gross_margin": 14.81, "debt_ratio": 69.87}, {"symbol": "sh600490", "train_return": 0.012756041221198269, "val_return": 0.058094951870583784, "test_return": 0.05875240384075637, "train_count": 68, "val_count": 44, "test_count": 47, "train_win_rate": 0.4852941176470588, "val_win_rate": 0.6818181818181818, "test_win_rate": 0.5106382978723404, "roe": 3.77, "revenue_growth": 26.83, "profit_growth": 299.98, "gross_margin": 11.68, "debt_ratio": 22.21}, {"symbol": "sz002246", "train_return": 0.022355996520338248, "val_return": 0.03365939373877633, "test_return": 0.054663651312795845, "train_count": 125, "val_count": 64, "test_count": 40, "train_win_rate": 0.56, "val_win_rate": 0.6875, "test_win_rate": 0.675, "roe": 6.47, "revenue_growth": 41.09, "profit_growth": 504.8, "gross_margin": 29.32, "debt_ratio": 35.56}, {"symbol": "sh688308", "train_return": 0.01387906470439753, "val_return": 0.0032037476951350453, "test_return": 0.054509447909887175, "train_count": 117, "val_count": 33, "test_count": 43, "train_win_rate": 0.5042735042735043, "val_win_rate": 0.5151515151515151, "test_win_rate": 0.6046511627906976, "roe": 1.98, "revenue_growth": 14.34, "profit_growth": -43.09, "gross_margin": 19.56, "debt_ratio": 32.83}, {"symbol": "sh603389", "train_return": 0.006840502444300804, "val_return": 0.04252435064133881, "test_return": 0.053864445753582034, "train_count": 98, "val_count": 44, "test_count": 42, "train_win_rate": 0.5204081632653061, "val_win_rate": 0.6590909090909091, "test_win_rate": 0.6428571428571429, "roe": -12.73, "revenue_growth": 4.2, "profit_growth": 41.15, "gross_margin": 23.79, "debt_ratio": 76.52}, {"symbol": "sz920533", "train_return": 0.018938709848761524, "val_return": 0.10450667094229392, "test_return": 0.05244814088130142, "train_count": 57, "val_count": 33, "test_count": 33, "train_win_rate": 0.543859649122807, "val_win_rate": 0.6060606060606061, "test_win_rate": 0.5151515151515151, "roe": 5.83, "revenue_growth": -12.03, "profit_growth": -54.24, "gross_margin": 22.14, "debt_ratio": 59.43}, {"symbol": "sz300042", "train_return": 0.0018776624571807399, "val_return": 0.016685572359758094, "test_return": 0.05170952910589838, "train_count": 83, "val_count": 37, "test_count": 41, "train_win_rate": 0.5180722891566265, "val_win_rate": 0.6216216216216216, "test_win_rate": 0.7073170731707317, "roe": -2.8, "revenue_growth": 35.19, "profit_growth": 58.26, "gross_margin": 7.9, "debt_ratio": 22.3}, {"symbol": "sz002645", "train_return": 0.02278163782113059, "val_return": 0.016774712869380193, "test_return": 0.04921773574347499, "train_count": 64, "val_count": 39, "test_count": 32, "train_win_rate": 0.5625, "val_win_rate": 0.48717948717948717, "test_win_rate": 0.59375, "roe": 5.73, "revenue_growth": 34.94, "profit_growth": 7110.7, "gross_margin": 11.07, "debt_ratio": 38.19}, {"symbol": "sh688630", "train_return": 0.012843277892946928, "val_return": 0.004277587866552602, "test_return": 0.04765769882130544, "train_count": 83, "val_count": 45, "test_count": 44, "train_win_rate": 0.5180722891566265, "val_win_rate": 0.5111111111111111, "test_win_rate": 0.5909090909090909, "roe": 13.28, "revenue_growth": 47.61, "profit_growth": 80.42, "gross_margin": 40.16, "debt_ratio": 25.93}, {"symbol": "sz300065", "train_return": 0.004492169461153466, "val_return": 0.03385918752368083, "test_return": 0.04587013586332359, "train_count": 60, "val_count": 42, "test_count": 50, "train_win_rate": 0.4666666666666667, "val_win_rate": 0.5238095238095238, "test_win_rate": 0.58, "roe": 2.3, "revenue_growth": 128.52, "profit_growth": 290.58, "gross_margin": 28.27, "debt_ratio": 21.83}, {"symbol": "sh600301", "train_return": 0.018435930926045632, "val_return": 0.028522539066936494, "test_return": 0.04576659162460431, "train_count": 66, "val_count": 44, "test_count": 38, "train_win_rate": 0.4696969696969697, "val_win_rate": 0.6136363636363636, "test_win_rate": 0.6578947368421053, "roe": 11.64, "revenue_growth": 21.16, "profit_growth": -8.54, "gross_margin": 34.37, "debt_ratio": 35.03}, {"symbol": "sh600236", "train_return": 0.013035677445736414, "val_return": 0.011713368044135301, "test_return": 0.045354363079718844, "train_count": 109, "val_count": 31, "test_count": 18, "train_win_rate": 0.5229357798165137, "val_win_rate": 0.41935483870967744, "test_win_rate": 0.5, "roe": 13.69, "revenue_growth": -0.25, "profit_growth": 11.8, "gross_margin": 55.61, "debt_ratio": 55.24}, {"symbol": "sz920779", "train_return": 0.021682338356793333, "val_return": 0.06135099824798559, "test_return": 0.045113488199049756, "train_count": 38, "val_count": 49, "test_count": 38, "train_win_rate": 0.5, "val_win_rate": 0.4897959183673469, "test_win_rate": 0.42105263157894735, "roe": 7.92, "revenue_growth": -13.56, "profit_growth": -29.19, "gross_margin": 59.66, "debt_ratio": 17.07}, {"symbol": "sz000409", "train_return": 0.00599341684227031, "val_return": 0.06323007464826505, "test_return": 0.04357402293493588, "train_count": 116, "val_count": 34, "test_count": 29, "train_win_rate": 0.4827586206896552, "val_win_rate": 0.7352941176470589, "test_win_rate": 0.5862068965517241, "roe": 3.28, "revenue_growth": 4.06, "profit_growth": -37.29, "gross_margin": 30.99, "debt_ratio": 31.21}, {"symbol": "sz003009", "train_return": 0.0025031208566791228, "val_return": 0.005934350472431768, "test_return": 0.04292561441213045, "train_count": 82, "val_count": 38, "test_count": 34, "train_win_rate": 0.5121951219512195, "val_win_rate": 0.4473684210526316, "test_win_rate": 0.5588235294117647, "roe": -1.83, "revenue_growth": -30.95, "profit_growth": -270.98, "gross_margin": 19.0, "debt_ratio": 46.51}, {"symbol": "sz300017", "train_return": 0.00947338115205343, "val_return": 0.009136710167481738, "test_return": 0.041786935355147485, "train_count": 119, "val_count": 48, "test_count": 18, "train_win_rate": 0.48739495798319327, "val_win_rate": 0.5, "test_win_rate": 0.4444444444444444, "roe": 6.05, "revenue_growth": -3.27, "profit_growth": 43.6, "gross_margin": 34.52, "debt_ratio": 15.23}, {"symbol": "sh603929", "train_return": 0.013726596475389275, "val_return": 0.02841578586616381, "test_return": 0.04138627570471122, "train_count": 121, "val_count": 26, "test_count": 32, "train_win_rate": 0.4462809917355372, "val_win_rate": 0.5, "test_win_rate": 0.71875, "roe": 43.55, "revenue_growth": -8.81, "profit_growth": 40.3, "gross_margin": 24.57, "debt_ratio": 57.01}, {"symbol": "sz300071", "train_return": 0.009719245653509293, "val_return": 0.0834742204721544, "test_return": 0.03957771912509703, "train_count": 95, "val_count": 65, "test_count": 38, "train_win_rate": 0.4631578947368421, "val_win_rate": 0.6, "test_win_rate": 0.631578947368421, "roe": -45.84, "revenue_growth": -17.83, "profit_growth": -79.6, "gross_margin": 24.52, "debt_ratio": 85.1}, {"symbol": "sz300927", "train_return": 0.01339549479221803, "val_return": 0.054276167258273375, "test_return": 0.03819591364521559, "train_count": 84, "val_count": 68, "test_count": 53, "train_win_rate": 0.44047619047619047, "val_win_rate": 0.5441176470588235, "test_win_rate": 0.5283018867924528, "roe": 0.85, "revenue_growth": 112.58, "profit_growth": -75.84, "gross_margin": 6.2, "debt_ratio": 53.18}, {"symbol": "sz300603", "train_return": 0.0009376263932618732, "val_return": 0.01634020629440456, "test_return": 0.03717200858847801, "train_count": 96, "val_count": 67, "test_count": 36, "train_win_rate": 0.5104166666666666, "val_win_rate": 0.5223880597014925, "test_win_rate": 0.5555555555555556, "roe": -4.18, "revenue_growth": 8.76, "profit_growth": -1184.24, "gross_margin": 7.04, "debt_ratio": 35.39}, {"symbol": "sz920425", "train_return": 0.0728831834779347, "val_return": 0.033383369396811136, "test_return": 0.03624658517460672, "train_count": 28, "val_count": 36, "test_count": 39, "train_win_rate": 0.5714285714285714, "val_win_rate": 0.4166666666666667, "test_win_rate": 0.4358974358974359, "roe": 9.11, "revenue_growth": 20.22, "profit_growth": 63.72, "gross_margin": 68.53, "debt_ratio": 6.51}, {"symbol": "sz300440", "train_return": 0.00675457802071574, "val_return": 0.00932284975064595, "test_return": 0.035863397065711344, "train_count": 82, "val_count": 26, "test_count": 21, "train_win_rate": 0.4268292682926829, "val_win_rate": 0.46153846153846156, "test_win_rate": 0.5714285714285714, "roe": 2.47, "revenue_growth": 4.31, "profit_growth": 1.34, "gross_margin": 40.58, "debt_ratio": 28.17}, {"symbol": "sz002633", "train_return": 0.0076468731115971866, "val_return": 0.060546355520079205, "test_return": 0.03533152105831104, "train_count": 112, "val_count": 44, "test_count": 20, "train_win_rate": 0.5714285714285714, "val_win_rate": 0.6590909090909091, "test_win_rate": 0.65, "roe": 1.45, "revenue_growth": -4.27, "profit_growth": -12.43, "gross_margin": 25.99, "debt_ratio": 34.3}, {"symbol": "sh603331", "train_return": 0.0063539378643963, "val_return": 0.02724510950263021, "test_return": 0.03483982502336907, "train_count": 52, "val_count": 43, "test_count": 32, "train_win_rate": 0.34615384615384615, "val_win_rate": 0.5813953488372093, "test_win_rate": 0.6875, "roe": 4.58, "revenue_growth": -0.59, "profit_growth": 178.85, "gross_margin": 21.51, "debt_ratio": 59.34}, {"symbol": "sz002517", "train_return": 0.013483703923539571, "val_return": 0.00741542110049193, "test_return": 0.03457562660651618, "train_count": 88, "val_count": 42, "test_count": 23, "train_win_rate": 0.5340909090909091, "val_win_rate": 0.47619047619047616, "test_win_rate": 0.6956521739130435, "roe": 20.78, "revenue_growth": 3.75, "profit_growth": 23.7, "gross_margin": 83.04, "debt_ratio": 22.43}, {"symbol": "sh601138", "train_return": 0.0021524148584571227, "val_return": 0.021404945200221417, "test_return": 0.03397711001977632, "train_count": 89, "val_count": 52, "test_count": 27, "train_win_rate": 0.449438202247191, "val_win_rate": 0.5, "test_win_rate": 0.5555555555555556, "roe": 21.65, "revenue_growth": 48.22, "profit_growth": 51.99, "gross_margin": 6.98, "debt_ratio": 63.37}, {"symbol": "sz920169", "train_return": 0.031740584868371814, "val_return": 0.10123949583284536, "test_return": 0.0333299967402573, "train_count": 55, "val_count": 35, "test_count": 41, "train_win_rate": 0.32727272727272727, "val_win_rate": 0.5142857142857142, "test_win_rate": 0.5121951219512195, "roe": 8.68, "revenue_growth": 15.91, "profit_growth": 259.66, "gross_margin": 23.6, "debt_ratio": 17.76}, {"symbol": "sz002121", "train_return": 0.006308382882435637, "val_return": 0.005489082037171727, "test_return": 0.032934544956451796, "train_count": 96, "val_count": 69, "test_count": 49, "train_win_rate": 0.40625, "val_win_rate": 0.6231884057971014, "test_win_rate": 0.6326530612244898, "roe": 37.41, "revenue_growth": 23.42, "profit_growth": 251.1, "gross_margin": 31.33, "debt_ratio": 90.59}, {"symbol": "sz300533", "train_return": 0.01573240603993376, "val_return": 0.04152881307044407, "test_return": 0.032522170521902045, "train_count": 103, "val_count": 72, "test_count": 48, "train_win_rate": 0.4563106796116505, "val_win_rate": 0.7361111111111112, "test_win_rate": 0.7291666666666666, "roe": 33.05, "revenue_growth": -5.39, "profit_growth": 207.49, "gross_margin": 93.03, "debt_ratio": 38.31}, {"symbol": "sh605169", "train_return": 0.0064048462281938, "val_return": 0.008400257517112006, "test_return": 0.0313676277910079, "train_count": 82, "val_count": 48, "test_count": 37, "train_win_rate": 0.4878048780487805, "val_win_rate": 0.5, "test_win_rate": 0.5135135135135135, "roe": 4.76, "revenue_growth": 16.72, "profit_growth": -43.96, "gross_margin": 11.27, "debt_ratio": 20.19}, {"symbol": "sh600265", "train_return": 0.009817386458016632, "val_return": 0.020914661500262145, "test_return": 0.0311719302983419, "train_count": 58, "val_count": 29, "test_count": 23, "train_win_rate": 0.41379310344827586, "val_win_rate": 0.5862068965517241, "test_win_rate": 0.6956521739130435, "roe": -410.21, "revenue_growth": -58.77, "profit_growth": -1701.7, "gross_margin": -19.68, "debt_ratio": 95.51}, {"symbol": "sh688663", "train_return": 0.0533504325890259, "val_return": 0.012475443813867651, "test_return": 0.030646026457346418, "train_count": 81, "val_count": 40, "test_count": 38, "train_win_rate": 0.5802469135802469, "val_win_rate": 0.725, "test_win_rate": 0.6578947368421053, "roe": 6.03, "revenue_growth": -6.62, "profit_growth": -33.54, "gross_margin": 23.12, "debt_ratio": 59.16}, {"symbol": "sz300818", "train_return": 0.0022413028969078797, "val_return": 0.029061722929017438, "test_return": 0.030249064452593125, "train_count": 99, "val_count": 45, "test_count": 39, "train_win_rate": 0.48484848484848486, "val_win_rate": 0.5555555555555556, "test_win_rate": 0.6923076923076923, "roe": 3.69, "revenue_growth": -22.46, "profit_growth": -48.07, "gross_margin": 41.7, "debt_ratio": 41.12}, {"symbol": "sz002460", "train_return": 0.001918826511962618, "val_return": 0.00666359090344472, "test_return": 0.029637342964123986, "train_count": 49, "val_count": 26, "test_count": 31, "train_win_rate": 0.40816326530612246, "val_win_rate": 0.46153846153846156, "test_win_rate": 0.6129032258064516, "roe": 0.06, "revenue_growth": 5.02, "profit_growth": 103.99, "gross_margin": 13.46, "debt_ratio": 57.59}, {"symbol": "sh600686", "train_return": 0.0020023451261278065, "val_return": 0.004196968778732692, "test_return": 0.029522561317259124, "train_count": 127, "val_count": 25, "test_count": 31, "train_win_rate": 0.41732283464566927, "val_win_rate": 0.6, "test_win_rate": 0.7741935483870968, "roe": 7.59, "revenue_growth": 13.4, "profit_growth": 223.71, "gross_margin": 12.31, "debt_ratio": 85.2}, {"symbol": "sz301205", "train_return": 0.14222018476327553, "val_return": 0.02281100141725455, "test_return": 0.028842533245134874, "train_count": 37, "val_count": 56, "test_count": 61, "train_win_rate": 0.7027027027027027, "val_win_rate": 0.625, "test_win_rate": 0.639344262295082, "roe": 5.24, "revenue_growth": 31.75, "profit_growth": 31.39, "gross_margin": 34.48, "debt_ratio": 42.55}, {"symbol": "sz300718", "train_return": 0.005116623096648101, "val_return": 0.0502261045738297, "test_return": 0.028414473592175707, "train_count": 73, "val_count": 48, "test_count": 21, "train_win_rate": 0.4520547945205479, "val_win_rate": 0.6458333333333334, "test_win_rate": 0.38095238095238093, "roe": 11.15, "revenue_growth": 11.97, "profit_growth": 11.01, "gross_margin": 34.86, "debt_ratio": 15.26}, {"symbol": "sz300490", "train_return": 0.012007478576552974, "val_return": 0.014296353268558973, "test_return": 0.028232647126722927, "train_count": 101, "val_count": 34, "test_count": 27, "train_win_rate": 0.46534653465346537, "val_win_rate": 0.5, "test_win_rate": 0.48148148148148145, "roe": -8.24, "revenue_growth": 7.88, "profit_growth": -33.39, "gross_margin": 13.45, "debt_ratio": 68.57}, {"symbol": "sz002350", "train_return": 0.02332534392168142, "val_return": 0.0069964027832308436, "test_return": 0.02819882688329941, "train_count": 106, "val_count": 73, "test_count": 57, "train_win_rate": 0.5660377358490566, "val_win_rate": 0.6027397260273972, "test_win_rate": 0.6491228070175439, "roe": 1.75, "revenue_growth": 14.16, "profit_growth": 1417.63, "gross_margin": 22.36, "debt_ratio": 41.62}, {"symbol": "sz002546", "train_return": 0.0016364151299848475, "val_return": 0.024462870339703423, "test_return": 0.027845079190837296, "train_count": 112, "val_count": 53, "test_count": 53, "train_win_rate": 0.5178571428571429, "val_win_rate": 0.6792452830188679, "test_win_rate": 0.7358490566037735, "roe": 15.12, "revenue_growth": -0.37, "profit_growth": 421.43, "gross_margin": 37.17, "debt_ratio": 8.21}, {"symbol": "sz301281", "train_return": 0.04979779307043153, "val_return": 0.07490655546345679, "test_return": 0.027502719164358137, "train_count": 28, "val_count": 46, "test_count": 47, "train_win_rate": 0.5, "val_win_rate": 0.4782608695652174, "test_win_rate": 0.5957446808510638, "roe": 2.3, "revenue_growth": -8.52, "profit_growth": -20.69, "gross_margin": 52.08, "debt_ratio": 14.6}, {"symbol": "sz300430", "train_return": 0.0013253741888089564, "val_return": 0.03685405434199734, "test_return": 0.026853802726465634, "train_count": 78, "val_count": 59, "test_count": 46, "train_win_rate": 0.4230769230769231, "val_win_rate": 0.5932203389830508, "test_win_rate": 0.5217391304347826, "roe": 3.0, "revenue_growth": -20.4, "profit_growth": -30.83, "gross_margin": 38.44, "debt_ratio": 39.65}, {"symbol": "sh600589", "train_return": 0.0031182252678319993, "val_return": 0.07392719058946959, "test_return": 0.026790338969583206, "train_count": 78, "val_count": 36, "test_count": 38, "train_win_rate": 0.4358974358974359, "val_win_rate": 0.5, "test_win_rate": 0.4473684210526316, "roe": 5.52, "revenue_growth": 2.28, "profit_growth": 236.78, "gross_margin": 20.6, "debt_ratio": 76.41}, {"symbol": "sh688456", "train_return": 0.014225412735954636, "val_return": 0.0151586372100537, "test_return": 0.025694884146816525, "train_count": 82, "val_count": 44, "test_count": 39, "train_win_rate": 0.524390243902439, "val_win_rate": 0.5, "test_win_rate": 0.5384615384615384, "roe": 4.17, "revenue_growth": 20.8, "profit_growth": 28.0, "gross_margin": 7.58, "debt_ratio": 41.19}, {"symbol": "sz920593", "train_return": 0.08609949124919421, "val_return": 0.07607703733928348, "test_return": 0.02517942935825032, "train_count": 25, "val_count": 38, "test_count": 48, "train_win_rate": 0.64, "val_win_rate": 0.6578947368421053, "test_win_rate": 0.5208333333333334, "roe": 3.91, "revenue_growth": 12.93, "profit_growth": -14.14, "gross_margin": 50.58, "debt_ratio": 8.68}, {"symbol": "sz301186", "train_return": 0.008834211008698094, "val_return": 0.021725415742478858, "test_return": 0.02474624356814684, "train_count": 73, "val_count": 56, "test_count": 42, "train_win_rate": 0.5205479452054794, "val_win_rate": 0.6428571428571429, "test_win_rate": 0.5952380952380952, "roe": 7.2, "revenue_growth": 8.5, "profit_growth": 44.17, "gross_margin": 36.52, "debt_ratio": 29.91}, {"symbol": "sz002228", "train_return": 0.0001699745016176945, "val_return": 0.022088040246689134, "test_return": 0.023849380069613076, "train_count": 56, "val_count": 53, "test_count": 32, "train_win_rate": 0.48214285714285715, "val_win_rate": 0.7358490566037735, "test_win_rate": 0.65625, "roe": 4.95, "revenue_growth": -9.84, "profit_growth": 10.52, "gross_margin": 13.47, "debt_ratio": 55.8}, {"symbol": "sz002126", "train_return": 0.002232637959333359, "val_return": 0.02061225421403144, "test_return": 0.023812983608746008, "train_count": 76, "val_count": 25, "test_count": 22, "train_win_rate": 0.4473684210526316, "val_win_rate": 0.6, "test_win_rate": 0.6363636363636364, "roe": 10.28, "revenue_growth": 20.12, "profit_growth": 11.18, "gross_margin": 19.3, "debt_ratio": 62.57}, {"symbol": "sh603380", "train_return": 0.012164920380279264, "val_return": 0.015202873204148787, "test_return": 0.023296960355362273, "train_count": 105, "val_count": 44, "test_count": 41, "train_win_rate": 0.5333333333333333, "val_win_rate": 0.5227272727272727, "test_win_rate": 0.5609756097560976, "roe": 11.53, "revenue_growth": 11.03, "profit_growth": 26.8, "gross_margin": 26.64, "debt_ratio": 33.64}, {"symbol": "sz002057", "train_return": 0.005160961146963171, "val_return": 0.023677698117508708, "test_return": 0.02325429121302208, "train_count": 72, "val_count": 57, "test_count": 50, "train_win_rate": 0.5277777777777778, "val_win_rate": 0.6491228070175439, "test_win_rate": 0.66, "roe": 6.94, "revenue_growth": 18.43, "profit_growth": 41.02, "gross_margin": 25.0, "debt_ratio": 30.87}, {"symbol": "sh688529", "train_return": 0.00020268906780311632, "val_return": 0.04222785407460879, "test_return": 0.022855576412004475, "train_count": 91, "val_count": 34, "test_count": 37, "train_win_rate": 0.4725274725274725, "val_win_rate": 0.5588235294117647, "test_win_rate": 0.4594594594594595, "roe": -13.46, "revenue_growth": -38.49, "profit_growth": -3462.54, "gross_margin": 14.65, "debt_ratio": 74.91}, {"symbol": "sz301191", "train_return": 0.03673433983833613, "val_return": 0.024454705543235707, "test_return": 0.022726040247788473, "train_count": 57, "val_count": 40, "test_count": 70, "train_win_rate": 0.5087719298245614, "val_win_rate": 0.5, "test_win_rate": 0.5571428571428572, "roe": 2.7, "revenue_growth": -1.81, "profit_growth": -55.26, "gross_margin": 12.77, "debt_ratio": 44.71}, {"symbol": "sz002496", "train_return": 0.007664123540749095, "val_return": 0.008963767333408541, "test_return": 0.02261168709341812, "train_count": 72, "val_count": 45, "test_count": 29, "train_win_rate": 0.5138888888888888, "val_win_rate": 0.5777777777777777, "test_win_rate": 0.6551724137931034, "roe": -0.24, "revenue_growth": 42.7, "profit_growth": -347.45, "gross_margin": 7.15, "debt_ratio": 43.56}, {"symbol": "sz300397", "train_return": 0.015841818587405104, "val_return": 0.03180492927661203, "test_return": 0.022606680617521743, "train_count": 69, "val_count": 41, "test_count": 42, "train_win_rate": 0.5217391304347826, "val_win_rate": 0.6585365853658537, "test_win_rate": 0.7142857142857143, "roe": -5.6, "revenue_growth": -3.36, "profit_growth": -30.0, "gross_margin": 26.69, "debt_ratio": 46.01}, {"symbol": "sz300509", "train_return": 0.00409856808742178, "val_return": 0.02657614627604855, "test_return": 0.02178448837690346, "train_count": 74, "val_count": 45, "test_count": 56, "train_win_rate": 0.581081081081081, "val_win_rate": 0.6888888888888889, "test_win_rate": 0.5714285714285714, "roe": 13.07, "revenue_growth": 15.88, "profit_growth": 191.95, "gross_margin": 27.35, "debt_ratio": 74.9}, {"symbol": "sh600233", "train_return": 0.012440260493707809, "val_return": 0.026900124548666332, "test_return": 0.02172197636683393, "train_count": 97, "val_count": 36, "test_count": 15, "train_win_rate": 0.4639175257731959, "val_win_rate": 0.6111111111111112, "test_win_rate": 0.6, "roe": 8.8, "revenue_growth": 9.69, "profit_growth": -1.83, "gross_margin": 8.87, "debt_ratio": 34.48}, {"symbol": "sh688306", "train_return": 0.0034121917373951967, "val_return": 0.03968633230365916, "test_return": 0.021505871654489212, "train_count": 70, "val_count": 42, "test_count": 51, "train_win_rate": 0.5142857142857142, "val_win_rate": 0.5238095238095238, "test_win_rate": 0.49019607843137253, "roe": -3.04, "revenue_growth": -4.09, "profit_growth": -11.42, "gross_margin": 20.29, "debt_ratio": 65.17}, {"symbol": "sh600633", "train_return": 0.004741594997511077, "val_return": 0.005040009795514054, "test_return": 0.021457357101953196, "train_count": 122, "val_count": 33, "test_count": 27, "train_win_rate": 0.5327868852459017, "val_win_rate": 0.5757575757575758, "test_win_rate": 0.6296296296296297, "roe": 5.24, "revenue_growth": -0.79, "profit_growth": 12.65, "gross_margin": 54.72, "debt_ratio": 11.54}, {"symbol": "sz300555", "train_return": 0.009261526055817659, "val_return": 0.03378683367279854, "test_return": 0.021376171634684363, "train_count": 99, "val_count": 36, "test_count": 41, "train_win_rate": 0.5454545454545454, "val_win_rate": 0.5555555555555556, "test_win_rate": 0.5609756097560976, "roe": -7.35, "revenue_growth": -26.68, "profit_growth": 1.25, "gross_margin": 13.62, "debt_ratio": 12.8}, {"symbol": "sz300787", "train_return": 0.008248215005148165, "val_return": 0.019624967602814954, "test_return": 0.02077509449395531, "train_count": 81, "val_count": 41, "test_count": 51, "train_win_rate": 0.5555555555555556, "val_win_rate": 0.6341463414634146, "test_win_rate": 0.7254901960784313, "roe": 5.34, "revenue_growth": 55.1, "profit_growth": 72.3, "gross_margin": 23.19, "debt_ratio": 60.37}, {"symbol": "sh603001", "train_return": 0.0009180673660675604, "val_return": 0.025264206221606942, "test_return": 0.020510486109684787, "train_count": 81, "val_count": 30, "test_count": 27, "train_win_rate": 0.6172839506172839, "val_win_rate": 0.6666666666666666, "test_win_rate": 0.5555555555555556, "roe": -8.32, "revenue_growth": -21.65, "profit_growth": -54.02, "gross_margin": 35.38, "debt_ratio": 23.85}, {"symbol": "sh603701", "train_return": 0.017093087074137578, "val_return": 0.019569892411200565, "test_return": 0.02032354968213508, "train_count": 88, "val_count": 47, "test_count": 45, "train_win_rate": 0.6022727272727273, "val_win_rate": 0.6595744680851063, "test_win_rate": 0.6666666666666666, "roe": 1.38, "revenue_growth": 34.29, "profit_growth": -24.8, "gross_margin": 14.01, "debt_ratio": 41.94}, {"symbol": "sz000599", "train_return": 0.006678324202671449, "val_return": 0.005668423987730721, "test_return": 0.02014546713571946, "train_count": 89, "val_count": 45, "test_count": 52, "train_win_rate": 0.38202247191011235, "val_win_rate": 0.37777777777777777, "test_win_rate": 0.4807692307692308, "roe": -17.91, "revenue_growth": 5.12, "profit_growth": -44.0, "gross_margin": 4.88, "debt_ratio": 84.25}, {"symbol": "sh600391", "train_return": 0.0007620921592106678, "val_return": 0.0085727428865718, "test_return": 0.02009844694675731, "train_count": 58, "val_count": 36, "test_count": 47, "train_win_rate": 0.43103448275862066, "val_win_rate": 0.5277777777777778, "test_win_rate": 0.48936170212765956, "roe": 1.72, "revenue_growth": 17.8, "profit_growth": -45.03, "gross_margin": 13.37, "debt_ratio": 63.48}, {"symbol": "sh600368", "train_return": 0.004248729053122016, "val_return": 0.02292605534521179, "test_return": 0.019999827749553705, "train_count": 90, "val_count": 50, "test_count": 17, "train_win_rate": 0.5555555555555556, "val_win_rate": 0.56, "test_win_rate": 0.29411764705882354, "roe": 7.25, "revenue_growth": -0.86, "profit_growth": -10.26, "gross_margin": 49.33, "debt_ratio": 32.85}, {"symbol": "sz002554", "train_return": 0.01614562612220376, "val_return": 0.006631570376339551, "test_return": 0.019931661589736374, "train_count": 63, "val_count": 30, "test_count": 22, "train_win_rate": 0.47619047619047616, "val_win_rate": 0.6, "test_win_rate": 0.5909090909090909, "roe": 0.45, "revenue_growth": -0.17, "profit_growth": 113.73, "gross_margin": 8.25, "debt_ratio": 58.49}, {"symbol": "sz920378", "train_return": 0.03282287242205786, "val_return": 0.06163101132569835, "test_return": 0.019593006989289244, "train_count": 18, "val_count": 41, "test_count": 22, "train_win_rate": 0.3888888888888889, "val_win_rate": 0.6097560975609756, "test_win_rate": 0.4090909090909091, "roe": 4.36, "revenue_growth": 15.05, "profit_growth": -27.13, "gross_margin": 24.72, "debt_ratio": 38.23}, {"symbol": "sz001267", "train_return": 0.015329101077299831, "val_return": 0.026946685475969234, "test_return": 0.01886203126483293, "train_count": 48, "val_count": 63, "test_count": 65, "train_win_rate": 0.3125, "val_win_rate": 0.5079365079365079, "test_win_rate": 0.5692307692307692, "roe": 3.29, "revenue_growth": 206.15, "profit_growth": 96.96, "gross_margin": 19.39, "debt_ratio": 52.37}, {"symbol": "sz920270", "train_return": 0.033643581948254835, "val_return": 0.05289045807622898, "test_return": 0.01855247604418792, "train_count": 51, "val_count": 40, "test_count": 40, "train_win_rate": 0.6274509803921569, "val_win_rate": 0.575, "test_win_rate": 0.475, "roe": 8.23, "revenue_growth": -12.2, "profit_growth": -27.08, "gross_margin": 40.6, "debt_ratio": 14.16}, {"symbol": "sz002132", "train_return": 0.022461367576932494, "val_return": 0.03917528600082012, "test_return": 0.018473583406727556, "train_count": 99, "val_count": 44, "test_count": 41, "train_win_rate": 0.5757575757575758, "val_win_rate": 0.7272727272727273, "test_win_rate": 0.4878048780487805, "roe": 0.57, "revenue_growth": 3.63, "profit_growth": 8.22, "gross_margin": 7.66, "debt_ratio": 58.06}, {"symbol": "sh603009", "train_return": 0.006966394473953108, "val_return": 0.04405011601327586, "test_return": 0.017983811213280507, "train_count": 123, "val_count": 52, "test_count": 27, "train_win_rate": 0.5853658536585366, "val_win_rate": 0.6923076923076923, "test_win_rate": 0.6666666666666666, "roe": 5.52, "revenue_growth": 17.5, "profit_growth": 52.39, "gross_margin": 19.86, "debt_ratio": 50.36}, {"symbol": "sh600667", "train_return": 0.005257171684262343, "val_return": 0.01463121482870253, "test_return": 0.017976083209254645, "train_count": 81, "val_count": 18, "test_count": 42, "train_win_rate": 0.4444444444444444, "val_win_rate": 0.5555555555555556, "test_win_rate": 0.6666666666666666, "roe": 5.1, "revenue_growth": -8.09, "profit_growth": -13.92, "gross_margin": 7.98, "debt_ratio": 71.69}, {"symbol": "sz000912", "train_return": 0.001975426818542658, "val_return": 0.016369648329584076, "test_return": 0.01785410230933014, "train_count": 73, "val_count": 34, "test_count": 20, "train_win_rate": 0.4657534246575342, "val_win_rate": 0.5588235294117647, "test_win_rate": 0.55, "roe": 0.5, "revenue_growth": -11.34, "profit_growth": 50.23, "gross_margin": 8.74, "debt_ratio": 32.47}, {"symbol": "sz002042", "train_return": 0.026485465964477203, "val_return": 0.05360748439764212, "test_return": 0.017817192411209635, "train_count": 46, "val_count": 42, "test_count": 33, "train_win_rate": 0.6086956521739131, "val_win_rate": 0.6904761904761905, "test_win_rate": 0.5151515151515151, "roe": 0.9, "revenue_growth": -4.86, "profit_growth": 9.51, "gross_margin": 5.64, "debt_ratio": 63.2}, {"symbol": "sz002448", "train_return": 0.00631570530939582, "val_return": 0.011325008231245054, "test_return": 0.01751796291751468, "train_count": 88, "val_count": 55, "test_count": 64, "train_win_rate": 0.6022727272727273, "val_win_rate": 0.5636363636363636, "test_win_rate": 0.625, "roe": 9.01, "revenue_growth": 16.35, "profit_growth": 39.89, "gross_margin": 27.88, "debt_ratio": 31.59}, {"symbol": "sh600067", "train_return": 0.00520493448761615, "val_return": 0.007201767788292602, "test_return": 0.016802490389087092, "train_count": 66, "val_count": 39, "test_count": 52, "train_win_rate": 0.42424242424242425, "val_win_rate": 0.48717948717948717, "test_win_rate": 0.5384615384615384, "roe": 1.43, "revenue_growth": 33.85, "profit_growth": 214.84, "gross_margin": 10.45, "debt_ratio": 59.73}, {"symbol": "sz300559", "train_return": 0.0005022153723260926, "val_return": 0.014394264169497756, "test_return": 0.01656353889638893, "train_count": 84, "val_count": 64, "test_count": 59, "train_win_rate": 0.4642857142857143, "val_win_rate": 0.59375, "test_win_rate": 0.6271186440677966, "roe": 4.01, "revenue_growth": 0.44, "profit_growth": -3.26, "gross_margin": 49.46, "debt_ratio": 23.17}, {"symbol": "sz920634", "train_return": 0.042225296040984364, "val_return": 0.013503630150605475, "test_return": 0.01615937755203438, "train_count": 41, "val_count": 54, "test_count": 46, "train_win_rate": 0.43902439024390244, "val_win_rate": 0.42592592592592593, "test_win_rate": 0.45652173913043476, "roe": 5.51, "revenue_growth": -4.56, "profit_growth": -32.5, "gross_margin": 7.7, "debt_ratio": 26.98}, {"symbol": "sz920879", "train_return": 0.027872880056241188, "val_return": 0.05361700374561717, "test_return": 0.016147539674962602, "train_count": 32, "val_count": 58, "test_count": 34, "train_win_rate": 0.59375, "val_win_rate": 0.6896551724137931, "test_win_rate": 0.5294117647058824, "roe": 8.89, "revenue_growth": 13.93, "profit_growth": 16.02, "gross_margin": 53.45, "debt_ratio": 17.79}, {"symbol": "sh603615", "train_return": 0.01837302112406289, "val_return": 0.017630908319414634, "test_return": 0.015845121485100592, "train_count": 96, "val_count": 46, "test_count": 21, "train_win_rate": 0.6354166666666666, "val_win_rate": 0.6304347826086957, "test_win_rate": 0.5714285714285714, "roe": 0.52, "revenue_growth": 113.92, "profit_growth": 139.79, "gross_margin": 11.49, "debt_ratio": 31.37}, {"symbol": "sz920856", "train_return": 0.022510070895905496, "val_return": 0.038858488476020754, "test_return": 0.015770948839822916, "train_count": 59, "val_count": 51, "test_count": 43, "train_win_rate": 0.5084745762711864, "val_win_rate": 0.5098039215686274, "test_win_rate": 0.3488372093023256, "roe": 3.86, "revenue_growth": 9.56, "profit_growth": 691.62, "gross_margin": 22.5, "debt_ratio": 31.16}, {"symbol": "sh600853", "train_return": 0.00788268011241121, "val_return": 0.000895464853689729, "test_return": 0.01574268588193366, "train_count": 94, "val_count": 31, "test_count": 30, "train_win_rate": 0.48936170212765956, "val_win_rate": 0.41935483870967744, "test_win_rate": 0.7333333333333333, "roe": 6.71, "revenue_growth": -3.57, "profit_growth": 9.51, "gross_margin": 13.37, "debt_ratio": 81.38}, {"symbol": "sz003021", "train_return": 0.014228361032635462, "val_return": 0.037071966138781776, "test_return": 0.015621303588295679, "train_count": 114, "val_count": 48, "test_count": 42, "train_win_rate": 0.5263157894736842, "val_win_rate": 0.5833333333333334, "test_win_rate": 0.5714285714285714, "roe": 5.51, "revenue_growth": 18.7, "profit_growth": 13.86, "gross_margin": 32.24, "debt_ratio": 19.58}, {"symbol": "sh601137", "train_return": 0.007040303934010979, "val_return": 0.011055436608510088, "test_return": 0.015573616398360602, "train_count": 101, "val_count": 47, "test_count": 46, "train_win_rate": 0.45544554455445546, "val_win_rate": 0.40425531914893614, "test_win_rate": 0.45652173913043476, "roe": 10.16, "revenue_growth": 6.07, "profit_growth": -19.76, "gross_margin": 13.2, "debt_ratio": 55.54}, {"symbol": "sz002366", "train_return": 0.0069067083929434244, "val_return": 0.009803829177270225, "test_return": 0.015540896813206936, "train_count": 100, "val_count": 54, "test_count": 26, "train_win_rate": 0.46, "val_win_rate": 0.5, "test_win_rate": 0.46153846153846156, "roe": -1.59, "revenue_growth": 5.49, "profit_growth": -460.9, "gross_margin": 11.06, "debt_ratio": 36.12}, {"symbol": "sz300315", "train_return": 0.020660560497868262, "val_return": 0.01693368374780686, "test_return": 0.015166308101769648, "train_count": 95, "val_count": 49, "test_count": 38, "train_win_rate": 0.5052631578947369, "val_win_rate": 0.6122448979591837, "test_win_rate": 0.5263157894736842, "roe": 1.56, "revenue_growth": -17.88, "profit_growth": -60.93, "gross_margin": 73.49, "debt_ratio": 7.73}, {"symbol": "sz002162", "train_return": 0.007714105279154519, "val_return": 0.008420858417090274, "test_return": 0.01515381271370908, "train_count": 85, "val_count": 50, "test_count": 54, "train_win_rate": 0.4823529411764706, "val_win_rate": 0.52, "test_win_rate": 0.5370370370370371, "roe": 0.38, "revenue_growth": -13.23, "profit_growth": 109.33, "gross_margin": 21.83, "debt_ratio": 58.31}, {"symbol": "sh688150", "train_return": 0.019811709398961482, "val_return": 0.005778666935696363, "test_return": 0.014959170771608498, "train_count": 64, "val_count": 33, "test_count": 29, "train_win_rate": 0.546875, "val_win_rate": 0.45454545454545453, "test_win_rate": 0.4482758620689655, "roe": 9.79, "revenue_growth": 18.77, "profit_growth": 38.62, "gross_margin": 74.17, "debt_ratio": 17.75}, {"symbol": "sz300753", "train_return": 0.011080037623659132, "val_return": 0.017516756881721704, "test_return": 0.01464501572616187, "train_count": 94, "val_count": 70, "test_count": 54, "train_win_rate": 0.4148936170212766, "val_win_rate": 0.5428571428571428, "test_win_rate": 0.5370370370370371, "roe": -1.66, "revenue_growth": -8.41, "profit_growth": -401.64, "gross_margin": 64.9, "debt_ratio": 18.29}, {"symbol": "sh600618", "train_return": 0.027095563996326934, "val_return": 0.007952847062637733, "test_return": 0.014508240205862596, "train_count": 69, "val_count": 34, "test_count": 48, "train_win_rate": 0.5942028985507246, "val_win_rate": 0.4411764705882353, "test_win_rate": 0.5208333333333334, "roe": 6.92, "revenue_growth": -5.36, "profit_growth": 1.02, "gross_margin": 14.81, "debt_ratio": 34.38}, {"symbol": "sh601098", "train_return": 0.002595759472278756, "val_return": 0.0019253603909413393, "test_return": 0.014484218267677335, "train_count": 82, "val_count": 28, "test_count": 13, "train_win_rate": 0.4634146341463415, "val_win_rate": 0.42857142857142855, "test_win_rate": 0.46153846153846156, "roe": 7.45, "revenue_growth": -9.37, "profit_growth": 22.32, "gross_margin": 46.12, "debt_ratio": 38.3}, {"symbol": "sz000856", "train_return": 0.0010851772350432096, "val_return": 0.008237254638845407, "test_return": 0.014468410744855742, "train_count": 116, "val_count": 38, "test_count": 23, "train_win_rate": 0.49137931034482757, "val_win_rate": 0.6052631578947368, "test_win_rate": 0.5217391304347826, "roe": 1.93, "revenue_growth": 7.12, "profit_growth": -27.74, "gross_margin": 6.81, "debt_ratio": 80.49}, {"symbol": "sz300447", "train_return": 0.0006915696440368292, "val_return": 0.01034880702447139, "test_return": 0.014287862625149125, "train_count": 139, "val_count": 60, "test_count": 50, "train_win_rate": 0.4892086330935252, "val_win_rate": 0.6, "test_win_rate": 0.6, "roe": 1.58, "revenue_growth": -16.64, "profit_growth": -46.24, "gross_margin": 38.06, "debt_ratio": 21.68}, {"symbol": "sz002579", "train_return": 0.01159955327030991, "val_return": 0.018881728243209425, "test_return": 0.014247473521890356, "train_count": 110, "val_count": 39, "test_count": 23, "train_win_rate": 0.5181818181818182, "val_win_rate": 0.48717948717948717, "test_win_rate": 0.43478260869565216, "roe": 1.06, "revenue_growth": 15.75, "profit_growth": 127.34, "gross_margin": 16.46, "debt_ratio": 60.47}, {"symbol": "sz300716", "train_return": 0.004427333065422348, "val_return": 0.024396618218071882, "test_return": 0.014141185416654376, "train_count": 92, "val_count": 55, "test_count": 29, "train_win_rate": 0.5108695652173914, "val_win_rate": 0.6181818181818182, "test_win_rate": 0.4827586206896552, "roe": null, "revenue_growth": -77.24, "profit_growth": 15.31, "gross_margin": -32.01, "debt_ratio": 109.06}, {"symbol": "sh600629", "train_return": 0.003590043528191155, "val_return": 0.027922801285295673, "test_return": 0.014057534612541289, "train_count": 97, "val_count": 37, "test_count": 40, "train_win_rate": 0.4948453608247423, "val_win_rate": 0.40540540540540543, "test_win_rate": 0.6, "roe": 2.98, "revenue_growth": -15.25, "profit_growth": -37.25, "gross_margin": 21.81, "debt_ratio": 62.99}, {"symbol": "sh600293", "train_return": 0.011976585198551198, "val_return": 0.008612027109810004, "test_return": 0.014048437947737384, "train_count": 89, "val_count": 43, "test_count": 42, "train_win_rate": 0.47191011235955055, "val_win_rate": 0.5348837209302325, "test_win_rate": 0.5476190476190477, "roe": -3.49, "revenue_growth": -27.29, "profit_growth": -525.45, "gross_margin": -0.75, "debt_ratio": 44.72}, {"symbol": "sh600284", "train_return": 0.004051715169957893, "val_return": 0.0012848060174667371, "test_return": 0.013512662757637624, "train_count": 98, "val_count": 44, "test_count": 30, "train_win_rate": 0.5714285714285714, "val_win_rate": 0.4772727272727273, "test_win_rate": 0.5333333333333333, "roe": 3.09, "revenue_growth": -30.35, "profit_growth": -47.73, "gross_margin": 7.29, "debt_ratio": 73.77}, {"symbol": "sz002094", "train_return": 0.0001694497524093554, "val_return": 0.00611767897006954, "test_return": 0.013285672371645369, "train_count": 85, "val_count": 47, "test_count": 44, "train_win_rate": 0.4823529411764706, "val_win_rate": 0.2978723404255319, "test_win_rate": 0.4090909090909091, "roe": 4.5, "revenue_growth": -8.5, "profit_growth": 4.34, "gross_margin": 20.43, "debt_ratio": 51.22}, {"symbol": "sz300218", "train_return": 0.010979470641256392, "val_return": 0.0027186877730101485, "test_return": 0.013272280344958034, "train_count": 103, "val_count": 51, "test_count": 46, "train_win_rate": 0.5339805825242718, "val_win_rate": 0.5294117647058824, "test_win_rate": 0.6086956521739131, "roe": 8.18, "revenue_growth": -6.84, "profit_growth": -19.22, "gross_margin": 25.22, "debt_ratio": 30.67}, {"symbol": "sh600743", "train_return": 0.0006535593613150944, "val_return": 0.06816063359532412, "test_return": 0.013176199741329945, "train_count": 83, "val_count": 32, "test_count": 13, "train_win_rate": 0.4457831325301205, "val_win_rate": 0.625, "test_win_rate": 0.46153846153846156, "roe": -5.61, "revenue_growth": -93.6, "profit_growth": 94.98, "gross_margin": 34.45, "debt_ratio": 63.65}, {"symbol": "sz002537", "train_return": 0.00023753197398946894, "val_return": 0.018062373052319173, "test_return": 0.013127211482719907, "train_count": 74, "val_count": 30, "test_count": 45, "train_win_rate": 0.43243243243243246, "val_win_rate": 0.4, "test_win_rate": 0.4666666666666667, "roe": 4.88, "revenue_growth": -14.42, "profit_growth": 354.05, "gross_margin": 14.95, "debt_ratio": 53.19}, {"symbol": "sh688401", "train_return": 0.006961807477849923, "val_return": 0.012704820164970494, "test_return": 0.012982278051423672, "train_count": 32, "val_count": 44, "test_count": 41, "train_win_rate": 0.53125, "val_win_rate": 0.4318181818181818, "test_win_rate": 0.3902439024390244, "roe": 11.58, "revenue_growth": 37.25, "profit_growth": 41.88, "gross_margin": 34.61, "debt_ratio": 45.12}, {"symbol": "sz002728", "train_return": 0.007928555524605889, "val_return": 0.008538427579013269, "test_return": 0.01279718551927456, "train_count": 92, "val_count": 37, "test_count": 32, "train_win_rate": 0.41304347826086957, "val_win_rate": 0.4864864864864865, "test_win_rate": 0.5625, "roe": 3.65, "revenue_growth": 51.86, "profit_growth": 985.18, "gross_margin": 56.94, "debt_ratio": 18.81}, {"symbol": "sz002555", "train_return": 0.01501931320922805, "val_return": 0.0004007265387577923, "test_return": 0.012688257095557251, "train_count": 90, "val_count": 53, "test_count": 23, "train_win_rate": 0.5444444444444444, "val_win_rate": 0.41509433962264153, "test_win_rate": 0.5217391304347826, "roe": 17.38, "revenue_growth": -6.59, "profit_growth": 23.57, "gross_margin": 76.76, "debt_ratio": 36.29}, {"symbol": "sz002187", "train_return": 0.004261758430695446, "val_return": 0.09109397703846334, "test_return": 0.012538323085845066, "train_count": 96, "val_count": 28, "test_count": 32, "train_win_rate": 0.4895833333333333, "val_win_rate": 0.7857142857142857, "test_win_rate": 0.5, "roe": -0.77, "revenue_growth": -31.6, "profit_growth": -159.01, "gross_margin": 26.31, "debt_ratio": 43.0}, {"symbol": "sz300703", "train_return": 0.0010714372994611635, "val_return": 0.046227889000918905, "test_return": 0.012395351760528056, "train_count": 86, "val_count": 45, "test_count": 40, "train_win_rate": 0.4883720930232558, "val_win_rate": 0.5555555555555556, "test_win_rate": 0.475, "roe": 8.58, "revenue_growth": 15.63, "profit_growth": 33.44, "gross_margin": 34.13, "debt_ratio": 50.61}, {"symbol": "sh605499", "train_return": 0.006586354354077906, "val_return": 0.023995666526344356, "test_return": 0.012323105747225786, "train_count": 80, "val_count": 54, "test_count": 15, "train_win_rate": 0.5375, "val_win_rate": 0.5925925925925926, "test_win_rate": 0.3333333333333333, "roe": 43.35, "revenue_growth": 34.13, "profit_growth": 38.91, "gross_margin": 45.17, "debt_ratio": 63.24}, {"symbol": "sz300881", "train_return": 0.0026830210613844993, "val_return": 0.0005861095219826437, "test_return": 0.012318821043057704, "train_count": 124, "val_count": 49, "test_count": 22, "train_win_rate": 0.47580645161290325, "val_win_rate": 0.42857142857142855, "test_win_rate": 0.5909090909090909, "roe": 13.44, "revenue_growth": 19.01, "profit_growth": -21.38, "gross_margin": 15.51, "debt_ratio": 63.91}, {"symbol": "sz300484", "train_return": 0.023197576484287444, "val_return": 0.07088171382384974, "test_return": 0.012308505805261917, "train_count": 98, "val_count": 52, "test_count": 44, "train_win_rate": 0.5918367346938775, "val_win_rate": 0.5961538461538461, "test_win_rate": 0.5, "roe": 7.02, "revenue_growth": 50.38, "profit_growth": 126.5, "gross_margin": 37.25, "debt_ratio": 28.93}, {"symbol": "sz920225", "train_return": 0.031778362778597455, "val_return": 0.018682910573611305, "test_return": 0.01224053206200598, "train_count": 90, "val_count": 50, "test_count": 46, "train_win_rate": 0.6, "val_win_rate": 0.56, "test_win_rate": 0.5, "roe": 9.39, "revenue_growth": 4.64, "profit_growth": -3.92, "gross_margin": 41.04, "debt_ratio": 20.96}, {"symbol": "sz300105", "train_return": 0.014356711166727095, "val_return": 0.017551874590268936, "test_return": 0.011863610811552633, "train_count": 143, "val_count": 72, "test_count": 48, "train_win_rate": 0.5104895104895105, "val_win_rate": 0.6805555555555556, "test_win_rate": 0.6666666666666666, "roe": 1.95, "revenue_growth": -9.3, "profit_growth": 61.51, "gross_margin": 25.3, "debt_ratio": 29.18}, {"symbol": "sh600266", "train_return": 0.0121831994949447, "val_return": 0.05603809818289329, "test_return": 0.01179497064136688, "train_count": 100, "val_count": 35, "test_count": 31, "train_win_rate": 0.44, "val_win_rate": 0.6285714285714286, "test_win_rate": 0.45161290322580644, "roe": 3.22, "revenue_growth": 64.2, "profit_growth": 40.24, "gross_margin": 19.84, "debt_ratio": 76.88}, {"symbol": "sh603053", "train_return": 0.0022362136295496094, "val_return": 0.001617419277163114, "test_return": 0.011754606118416631, "train_count": 93, "val_count": 38, "test_count": 26, "train_win_rate": 0.5376344086021505, "val_win_rate": 0.631578947368421, "test_win_rate": 0.5769230769230769, "roe": 8.69, "revenue_growth": -0.78, "profit_growth": -0.84, "gross_margin": 21.25, "debt_ratio": 39.18}, {"symbol": "sz002752", "train_return": 0.008055539863342932, "val_return": 0.013493161540764971, "test_return": 0.011634716474298732, "train_count": 95, "val_count": 29, "test_count": 36, "train_win_rate": 0.6421052631578947, "val_win_rate": 0.7241379310344828, "test_win_rate": 0.5555555555555556, "roe": 8.82, "revenue_growth": 0.61, "profit_growth": -27.44, "gross_margin": 11.03, "debt_ratio": 54.07}, {"symbol": "sh603508", "train_return": 0.008899816657897026, "val_return": 0.010527410957923467, "test_return": 0.011532514703415165, "train_count": 94, "val_count": 56, "test_count": 38, "train_win_rate": 0.5106382978723404, "val_win_rate": 0.42857142857142855, "test_win_rate": 0.5, "roe": 8.51, "revenue_growth": 5.25, "profit_growth": 20.98, "gross_margin": 67.22, "debt_ratio": 7.21}, {"symbol": "sh601991", "train_return": 0.0033643686781348586, "val_return": 0.0036909559342662495, "test_return": 0.011156322156685858, "train_count": 91, "val_count": 61, "test_count": 45, "train_win_rate": 0.4835164835164835, "val_win_rate": 0.47540983606557374, "test_win_rate": 0.5777777777777777, "roe": 16.92, "revenue_growth": -1.82, "profit_growth": 51.48, "gross_margin": 19.41, "debt_ratio": 66.22}, {"symbol": "sz002963", "train_return": 0.007197920876315878, "val_return": 0.008154307987933016, "test_return": 0.011121606007790264, "train_count": 123, "val_count": 33, "test_count": 49, "train_win_rate": 0.5853658536585366, "val_win_rate": 0.6060606060606061, "test_win_rate": 0.6122448979591837, "roe": -1.97, "revenue_growth": -29.79, "profit_growth": -523.96, "gross_margin": 22.05, "debt_ratio": 25.22}, {"symbol": "sz300775", "train_return": 0.003250747658823399, "val_return": 0.001590938642146241, "test_return": 0.01110059689962076, "train_count": 55, "val_count": 27, "test_count": 36, "train_win_rate": 0.4, "val_win_rate": 0.3333333333333333, "test_win_rate": 0.5, "roe": 6.36, "revenue_growth": -8.51, "profit_growth": 25.64, "gross_margin": 42.9, "debt_ratio": 30.02}, {"symbol": "sh600459", "train_return": 0.01381273251062366, "val_return": 0.02395097998705166, "test_return": 0.011066933771607708, "train_count": 77, "val_count": 36, "test_count": 44, "train_win_rate": 0.6233766233766234, "val_win_rate": 0.75, "test_win_rate": 0.5681818181818182, "roe": 6.86, "revenue_growth": 22.21, "profit_growth": 12.43, "gross_margin": 2.28, "debt_ratio": 64.02}, {"symbol": "sz920367", "train_return": 0.06537980971249753, "val_return": 0.054974529947793366, "test_return": 0.010954799113637668, "train_count": 31, "val_count": 55, "test_count": 43, "train_win_rate": 0.3870967741935484, "val_win_rate": 0.5272727272727272, "test_win_rate": 0.3953488372093023, "roe": 1.75, "revenue_growth": -12.69, "profit_growth": -59.02, "gross_margin": 43.98, "debt_ratio": 12.69}, {"symbol": "sz920821", "train_return": 0.07515563529178133, "val_return": 0.02178044457085089, "test_return": 0.010833639217446647, "train_count": 39, "val_count": 59, "test_count": 45, "train_win_rate": 0.41025641025641024, "val_win_rate": 0.4406779661016949, "test_win_rate": 0.4888888888888889, "roe": 2.82, "revenue_growth": 9.47, "profit_growth": -28.21, "gross_margin": 24.32, "debt_ratio": 36.65}, {"symbol": "sh688560", "train_return": 0.016513751719443883, "val_return": 0.03548653904198381, "test_return": 0.010618792819680587, "train_count": 57, "val_count": 44, "test_count": 49, "train_win_rate": 0.543859649122807, "val_win_rate": 0.5227272727272727, "test_win_rate": 0.42857142857142855, "roe": -2.73, "revenue_growth": -29.42, "profit_growth": -428.01, "gross_margin": -3.75, "debt_ratio": 7.43}, {"symbol": "sz002442", "train_return": 0.0030012325435745547, "val_return": 0.008998048256162579, "test_return": 0.01035063304750727, "train_count": 128, "val_count": 35, "test_count": 21, "train_win_rate": 0.4921875, "val_win_rate": 0.6285714285714286, "test_win_rate": 0.6666666666666666, "roe": 3.29, "revenue_growth": 3.76, "profit_growth": -45.59, "gross_margin": 8.62, "debt_ratio": 59.11}, {"symbol": "sz300068", "train_return": 0.002025373036671109, "val_return": 0.04800120587834186, "test_return": 0.010348137094925876, "train_count": 102, "val_count": 37, "test_count": 38, "train_win_rate": 0.46078431372549017, "val_win_rate": 0.4594594594594595, "test_win_rate": 0.5, "roe": -6.0, "revenue_growth": -24.8, "profit_growth": -189.22, "gross_margin": 11.71, "debt_ratio": 79.01}, {"symbol": "sh688685", "train_return": 0.0033402064802323162, "val_return": 0.043084248557369156, "test_return": 0.009949108566888056, "train_count": 72, "val_count": 32, "test_count": 38, "train_win_rate": 0.4444444444444444, "val_win_rate": 0.71875, "test_win_rate": 0.5526315789473685, "roe": 7.12, "revenue_growth": 48.42, "profit_growth": 55.17, "gross_margin": 50.39, "debt_ratio": 69.71}, {"symbol": "sz002267", "train_return": 0.004886014007643713, "val_return": 0.0006375783897504646, "test_return": 0.009895635446328698, "train_count": 88, "val_count": 33, "test_count": 27, "train_win_rate": 0.6136363636363636, "val_win_rate": 0.48484848484848486, "test_win_rate": 0.6296296296296297, "roe": 7.3, "revenue_growth": -7.38, "profit_growth": -23.85, "gross_margin": 15.42, "debt_ratio": 50.7}, {"symbol": "sz300770", "train_return": 0.009448930684280545, "val_return": 0.01129130960601081, "test_return": 0.009630274342077486, "train_count": 96, "val_count": 38, "test_count": 42, "train_win_rate": 0.5833333333333334, "val_win_rate": 0.5526315789473685, "test_win_rate": 0.5476190476190477, "roe": 13.55, "revenue_growth": 5.28, "profit_growth": 19.72, "gross_margin": 48.75, "debt_ratio": 22.93}, {"symbol": "sz300155", "train_return": 0.0151391954488225, "val_return": 0.07317856055025203, "test_return": 0.009534794152957918, "train_count": 67, "val_count": 60, "test_count": 47, "train_win_rate": 0.3582089552238806, "val_win_rate": 0.5333333333333333, "test_win_rate": 0.5531914893617021, "roe": -2.67, "revenue_growth": -30.48, "profit_growth": -56.06, "gross_margin": 35.92, "debt_ratio": 10.05}, {"symbol": "sz002653", "train_return": 0.004943851809363894, "val_return": 0.013719447881527505, "test_return": 0.009475340641678926, "train_count": 123, "val_count": 60, "test_count": 45, "train_win_rate": 0.4878048780487805, "val_win_rate": 0.55, "test_win_rate": 0.6, "roe": 7.08, "revenue_growth": 19.95, "profit_growth": -22.66, "gross_margin": 73.9, "debt_ratio": 41.43}, {"symbol": "sz002902", "train_return": 0.0331163451289262, "val_return": 0.07094507976765733, "test_return": 0.009399654202087137, "train_count": 86, "val_count": 24, "test_count": 39, "train_win_rate": 0.5813953488372093, "val_win_rate": 0.75, "test_win_rate": 0.6153846153846154, "roe": -14.96, "revenue_growth": -1.31, "profit_growth": -7.27, "gross_margin": 13.25, "debt_ratio": 66.36}, {"symbol": "sh603611", "train_return": 0.009189680519940192, "val_return": 0.008646844023637038, "test_return": 0.009333821261583532, "train_count": 103, "val_count": 53, "test_count": 20, "train_win_rate": 0.5048543689320388, "val_win_rate": 0.5660377358490566, "test_win_rate": 0.6, "roe": 12.87, "revenue_growth": -2.28, "profit_growth": 9.23, "gross_margin": 22.38, "debt_ratio": 66.61}, {"symbol": "sz301266", "train_return": 0.006061640069093955, "val_return": 0.005124981537997003, "test_return": 0.009293727492647227, "train_count": 69, "val_count": 59, "test_count": 63, "train_win_rate": 0.4782608695652174, "val_win_rate": 0.4406779661016949, "test_win_rate": 0.5396825396825397, "roe": 2.86, "revenue_growth": -8.75, "profit_growth": 13.63, "gross_margin": 6.4, "debt_ratio": 44.69}, {"symbol": "sz000070", "train_return": 0.0006325654171749692, "val_return": 0.014066348599522351, "test_return": 0.009236850935904149, "train_count": 125, "val_count": 36, "test_count": 31, "train_win_rate": 0.488, "val_win_rate": 0.5277777777777778, "test_win_rate": 0.41935483870967744, "roe": 0.53, "revenue_growth": -10.04, "profit_growth": 80.75, "gross_margin": 19.02, "debt_ratio": 71.02}, {"symbol": "sz002441", "train_return": 0.00389322561955623, "val_return": 0.010497125646636988, "test_return": 0.00920071717167222, "train_count": 71, "val_count": 71, "test_count": 54, "train_win_rate": 0.4788732394366197, "val_win_rate": 0.6338028169014085, "test_win_rate": 0.7037037037037037, "roe": 3.95, "revenue_growth": 0.61, "profit_growth": 29.37, "gross_margin": 8.61, "debt_ratio": 34.03}, {"symbol": "sh603019", "train_return": 0.018744386053299745, "val_return": 0.019107930470469315, "test_return": 0.00876487299395149, "train_count": 73, "val_count": 26, "test_count": 39, "train_win_rate": 0.4794520547945205, "val_win_rate": 0.46153846153846156, "test_win_rate": 0.48717948717948717, "roe": 4.67, "revenue_growth": 9.68, "profit_growth": 25.55, "gross_margin": 24.45, "debt_ratio": 40.67}, {"symbol": "sz002559", "train_return": 0.02403011526757773, "val_return": 0.019806954544453387, "test_return": 0.008726341376242714, "train_count": 123, "val_count": 37, "test_count": 41, "train_win_rate": 0.5691056910569106, "val_win_rate": 0.6756756756756757, "test_win_rate": 0.7317073170731707, "roe": 5.87, "revenue_growth": 6.33, "profit_growth": 0.21, "gross_margin": 21.58, "debt_ratio": 63.09}, {"symbol": "sz002096", "train_return": 0.0005694514747102986, "val_return": 0.0021936141988981575, "test_return": 0.008678437666415859, "train_count": 92, "val_count": 74, "test_count": 40, "train_win_rate": 0.5, "val_win_rate": 0.527027027027027, "test_win_rate": 0.45, "roe": 8.37, "revenue_growth": 16.7, "profit_growth": 22.91, "gross_margin": 24.15, "debt_ratio": 35.55}, {"symbol": "sh605186", "train_return": 0.007790030918200397, "val_return": 0.01706300340463477, "test_return": 0.008662927974317962, "train_count": 90, "val_count": 40, "test_count": 42, "train_win_rate": 0.5, "val_win_rate": 0.5, "test_win_rate": 0.47619047619047616, "roe": 0.79, "revenue_growth": 38.55, "profit_growth": -73.63, "gross_margin": 39.59, "debt_ratio": 26.52}, {"symbol": "sh603999", "train_return": 0.002285083036797658, "val_return": 0.012166580589471891, "test_return": 0.008641639172837627, "train_count": 94, "val_count": 43, "test_count": 55, "train_win_rate": 0.5425531914893617, "val_win_rate": 0.6046511627906976, "test_win_rate": 0.6181818181818182, "roe": 3.95, "revenue_growth": -14.69, "profit_growth": 11.15, "gross_margin": 26.89, "debt_ratio": 20.9}, {"symbol": "sz920163", "train_return": 0.01833475419521611, "val_return": 0.015119903582264812, "test_return": 0.008634131103541645, "train_count": 81, "val_count": 66, "test_count": 63, "train_win_rate": 0.43209876543209874, "val_win_rate": 0.4393939393939394, "test_win_rate": 0.42857142857142855, "roe": 6.11, "revenue_growth": 20.58, "profit_growth": -19.26, "gross_margin": 15.38, "debt_ratio": 45.64}, {"symbol": "sz002907", "train_return": 0.02072866596726773, "val_return": 0.005935693337023282, "test_return": 0.008578388007637796, "train_count": 71, "val_count": 58, "test_count": 41, "train_win_rate": 0.36619718309859156, "val_win_rate": 0.43103448275862066, "test_win_rate": 0.3902439024390244, "roe": 4.31, "revenue_growth": 1.9, "profit_growth": -2.84, "gross_margin": 58.22, "debt_ratio": 14.4}, {"symbol": "sz300541", "train_return": 0.004243660146918413, "val_return": 0.024592913353020013, "test_return": 0.008322025456804662, "train_count": 122, "val_count": 83, "test_count": 69, "train_win_rate": 0.5, "val_win_rate": 0.5542168674698795, "test_win_rate": 0.6231884057971014, "roe": 5.12, "revenue_growth": 49.83, "profit_growth": 163.1, "gross_margin": 13.91, "debt_ratio": 48.33}, {"symbol": "sz301366", "train_return": 0.03184002485558678, "val_return": 0.03342250674560346, "test_return": 0.008300873285081311, "train_count": 58, "val_count": 74, "test_count": 51, "train_win_rate": 0.603448275862069, "val_win_rate": 0.5945945945945946, "test_win_rate": 0.5098039215686274, "roe": 0.79, "revenue_growth": 24.01, "profit_growth": -79.46, "gross_margin": 28.0, "debt_ratio": 23.66}, {"symbol": "sz000695", "train_return": 0.011592128695450607, "val_return": 0.042272304906483205, "test_return": 0.008051166507377317, "train_count": 96, "val_count": 23, "test_count": 9, "train_win_rate": 0.46875, "val_win_rate": 0.6086956521739131, "test_win_rate": 0.4444444444444444, "roe": -37.37, "revenue_growth": 2.03, "profit_growth": -2837.15, "gross_margin": -0.7, "debt_ratio": 90.45}, {"symbol": "sh601609", "train_return": 0.0005794919291115118, "val_return": 0.02448958334124029, "test_return": 0.007661491574914834, "train_count": 60, "val_count": 36, "test_count": 23, "train_win_rate": 0.6, "val_win_rate": 0.75, "test_win_rate": 0.391304347826087, "roe": 6.85, "revenue_growth": -0.09, "profit_growth": 104.37, "gross_margin": 2.69, "debt_ratio": 63.81}, {"symbol": "sh603031", "train_return": 0.01922866707847814, "val_return": 0.007984599788604684, "test_return": 0.0075046068501714224, "train_count": 80, "val_count": 49, "test_count": 45, "train_win_rate": 0.5, "val_win_rate": 0.5306122448979592, "test_win_rate": 0.5111111111111111, "roe": 10.18, "revenue_growth": 2.94, "profit_growth": 34.38, "gross_margin": 49.43, "debt_ratio": 53.27}, {"symbol": "sz920030", "train_return": 0.03326525238143607, "val_return": 0.03158627299401862, "test_return": 0.007442957790103386, "train_count": 68, "val_count": 40, "test_count": 21, "train_win_rate": 0.45588235294117646, "val_win_rate": 0.5, "test_win_rate": 0.42857142857142855, "roe": -1.74, "revenue_growth": 7.3, "profit_growth": -275.67, "gross_margin": 6.71, "debt_ratio": 67.27}, {"symbol": "sz002357", "train_return": 0.006104745074513828, "val_return": 0.00916725494737734, "test_return": 0.007382600465357256, "train_count": 86, "val_count": 48, "test_count": 37, "train_win_rate": 0.5, "val_win_rate": 0.6041666666666666, "test_win_rate": 0.4594594594594595, "roe": 9.41, "revenue_growth": -4.9, "profit_growth": 73.16, "gross_margin": 18.63, "debt_ratio": 38.92}, {"symbol": "sz301321", "train_return": 0.014769178237638753, "val_return": 0.008480460718449004, "test_return": 0.007262004060749687, "train_count": 56, "val_count": 49, "test_count": 45, "train_win_rate": 0.44642857142857145, "val_win_rate": 0.46938775510204084, "test_win_rate": 0.4666666666666667, "roe": -0.86, "revenue_growth": 44.06, "profit_growth": 91.13, "gross_margin": 10.82, "debt_ratio": 79.47}, {"symbol": "sz002046", "train_return": 0.012754553655506247, "val_return": 0.017306190477465185, "test_return": 0.0072023397792872835, "train_count": 84, "val_count": 54, "test_count": 44, "train_win_rate": 0.4523809523809524, "val_win_rate": 0.5, "test_win_rate": 0.5, "roe": 5.0, "revenue_growth": 27.17, "profit_growth": 0.79, "gross_margin": 34.71, "debt_ratio": 28.19}, {"symbol": "sh603385", "train_return": 0.004215619330620622, "val_return": 0.024920884203669724, "test_return": 0.006984572909126819, "train_count": 66, "val_count": 40, "test_count": 22, "train_win_rate": 0.4696969696969697, "val_win_rate": 0.775, "test_win_rate": 0.6818181818181818, "roe": 0.4, "revenue_growth": -10.71, "profit_growth": -83.69, "gross_margin": 25.12, "debt_ratio": 24.94}, {"symbol": "sh600602", "train_return": 0.012174588002726139, "val_return": 0.0015729754304250204, "test_return": 0.006979070876808521, "train_count": 101, "val_count": 26, "test_count": 37, "train_win_rate": 0.5346534653465347, "val_win_rate": 0.5769230769230769, "test_win_rate": 0.5405405405405406, "roe": 3.02, "revenue_growth": 13.32, "profit_growth": -8.28, "gross_margin": 16.66, "debt_ratio": 39.0}, {"symbol": "sh600178", "train_return": 0.0065009402967882235, "val_return": 0.02629607869749925, "test_return": 0.006399646384139797, "train_count": 84, "val_count": 48, "test_count": 41, "train_win_rate": 0.5357142857142857, "val_win_rate": 0.5208333333333334, "test_win_rate": 0.5121951219512195, "roe": -0.17, "revenue_growth": 25.88, "profit_growth": -105.55, "gross_margin": 2.97, "debt_ratio": 54.49}, {"symbol": "sz002708", "train_return": 0.01514673115408018, "val_return": 0.000823789476698673, "test_return": 0.0062389903869338875, "train_count": 95, "val_count": 59, "test_count": 48, "train_win_rate": 0.5368421052631579, "val_win_rate": 0.5254237288135594, "test_win_rate": 0.4791666666666667, "roe": 3.81, "revenue_growth": 10.76, "profit_growth": 58.26, "gross_margin": 16.85, "debt_ratio": 54.31}, {"symbol": "sz301212", "train_return": 0.0018827588010266322, "val_return": 0.010754402737852787, "test_return": 0.0062099389779883525, "train_count": 57, "val_count": 59, "test_count": 55, "train_win_rate": 0.49122807017543857, "val_win_rate": 0.559322033898305, "test_win_rate": 0.5818181818181818, "roe": 0.92, "revenue_growth": 18.06, "profit_growth": -8.2, "gross_margin": 10.84, "debt_ratio": 20.98}, {"symbol": "sh603768", "train_return": 0.012515667571020612, "val_return": 0.02533877481332627, "test_return": 0.006079535715616791, "train_count": 79, "val_count": 43, "test_count": 19, "train_win_rate": 0.5189873417721519, "val_win_rate": 0.6511627906976745, "test_win_rate": 0.5789473684210527, "roe": -2.84, "revenue_growth": 4.23, "profit_growth": -196.37, "gross_margin": 14.56, "debt_ratio": 62.44}, {"symbol": "sz000978", "train_return": 0.017905694412051896, "val_return": 0.010070726483004796, "test_return": 0.00595554019367379, "train_count": 97, "val_count": 45, "test_count": 26, "train_win_rate": 0.5257731958762887, "val_win_rate": 0.5777777777777777, "test_win_rate": 0.6153846153846154, "roe": 3.28, "revenue_growth": -0.98, "profit_growth": 425.76, "gross_margin": 33.07, "debt_ratio": 51.37}, {"symbol": "sz300230", "train_return": 0.00592117756148066, "val_return": 0.016550804607675388, "test_return": 0.005945675570787343, "train_count": 61, "val_count": 44, "test_count": 46, "train_win_rate": 0.45901639344262296, "val_win_rate": 0.5454545454545454, "test_win_rate": 0.6086956521739131, "roe": 5.07, "revenue_growth": 8.66, "profit_growth": 0.75, "gross_margin": 31.45, "debt_ratio": 22.06}, {"symbol": "sz000848", "train_return": 0.0014412440755139692, "val_return": 0.013018467972269935, "test_return": 0.0059051220490473275, "train_count": 88, "val_count": 44, "test_count": 17, "train_win_rate": 0.48863636363636365, "val_win_rate": 0.5681818181818182, "test_win_rate": 0.5882352941176471, "roe": 11.0, "revenue_growth": -9.42, "profit_growth": -8.47, "gross_margin": 45.62, "debt_ratio": 25.44}, {"symbol": "sz000825", "train_return": 0.03927035549518236, "val_return": 0.0021635406672380394, "test_return": 0.005895695526047058, "train_count": 46, "val_count": 35, "test_count": 36, "train_win_rate": 0.5434782608695652, "val_win_rate": 0.34285714285714286, "test_win_rate": 0.4722222222222222, "roe": 1.73, "revenue_growth": -9.67, "profit_growth": 202.48, "gross_margin": 2.46, "debt_ratio": 46.36}, {"symbol": "sh600841", "train_return": 0.011307348022244538, "val_return": 0.019280156305471217, "test_return": 0.005738235031794846, "train_count": 54, "val_count": 28, "test_count": 25, "train_win_rate": 0.5370370370370371, "val_win_rate": 0.5357142857142857, "test_win_rate": 0.52, "roe": -10.39, "revenue_growth": -20.34, "profit_growth": 72.32, "gross_margin": 6.87, "debt_ratio": 76.23}, {"symbol": "sh601000", "train_return": 0.0034889205391580415, "val_return": 0.01929303377808198, "test_return": 0.005643135597589386, "train_count": 117, "val_count": 36, "test_count": 23, "train_win_rate": 0.452991452991453, "val_win_rate": 0.5833333333333334, "test_win_rate": 0.5217391304347826, "roe": 6.63, "revenue_growth": -4.47, "profit_growth": -12.22, "gross_margin": 46.58, "debt_ratio": 9.45}, {"symbol": "sz002588", "train_return": 0.004567182994727202, "val_return": 0.004437351949560868, "test_return": 0.005525763056332686, "train_count": 97, "val_count": 47, "test_count": 42, "train_win_rate": 0.4742268041237113, "val_win_rate": 0.48936170212765956, "test_win_rate": 0.5952380952380952, "roe": 11.48, "revenue_growth": 17.91, "profit_growth": 22.71, "gross_margin": 18.01, "debt_ratio": 45.28}, {"symbol": "sh603867", "train_return": 0.003724732412516287, "val_return": 0.0068982540966642, "test_return": 0.005172947589478381, "train_count": 76, "val_count": 35, "test_count": 25, "train_win_rate": 0.5394736842105263, "val_win_rate": 0.45714285714285713, "test_win_rate": 0.52, "roe": 7.59, "revenue_growth": 0.36, "profit_growth": 2.66, "gross_margin": 22.32, "debt_ratio": 37.2}, {"symbol": "sh601369", "train_return": 0.009815846699910391, "val_return": 0.0036629294492648095, "test_return": 0.0050215943617966195, "train_count": 77, "val_count": 33, "test_count": 38, "train_win_rate": 0.5714285714285714, "val_win_rate": 0.48484848484848486, "test_win_rate": 0.5526315789473685, "roe": 6.83, "revenue_growth": -1.42, "profit_growth": -7.31, "gross_margin": 21.31, "debt_ratio": 61.4}, {"symbol": "sh600234", "train_return": 0.020646502014980247, "val_return": 0.007422364035406216, "test_return": 0.004970073301572708, "train_count": 80, "val_count": 24, "test_count": 45, "train_win_rate": 0.575, "val_win_rate": 0.3333333333333333, "test_win_rate": 0.4666666666666667, "roe": 6.49, "revenue_growth": 66.92, "profit_growth": 170.94, "gross_margin": 13.47, "debt_ratio": 39.11}, {"symbol": "sz002198", "train_return": 0.006319536123749966, "val_return": 0.0015760482645315384, "test_return": 0.0049389714848897025, "train_count": 92, "val_count": 33, "test_count": 38, "train_win_rate": 0.44565217391304346, "val_win_rate": 0.36363636363636365, "test_win_rate": 0.5526315789473685, "roe": 2.97, "revenue_growth": 13.03, "profit_growth": 658.5, "gross_margin": 56.41, "debt_ratio": 8.48}, {"symbol": "sz920685", "train_return": 0.006676677062811738, "val_return": 0.021344633191935785, "test_return": 0.004831177970815845, "train_count": 26, "val_count": 53, "test_count": 43, "train_win_rate": 0.38461538461538464, "val_win_rate": 0.5471698113207547, "test_win_rate": 0.4418604651162791, "roe": 3.82, "revenue_growth": 5.04, "profit_growth": -4.36, "gross_margin": 62.7, "debt_ratio": 11.69}, {"symbol": "sh600563", "train_return": 0.007134106289673458, "val_return": 0.021824261757582952, "test_return": 0.0047916333381847614, "train_count": 87, "val_count": 49, "test_count": 50, "train_win_rate": 0.5632183908045977, "val_win_rate": 0.5918367346938775, "test_win_rate": 0.6, "roe": 16.12, "revenue_growth": 14.69, "profit_growth": 14.58, "gross_margin": 32.88, "debt_ratio": 30.86}, {"symbol": "sh601328", "train_return": 0.005696270701396082, "val_return": 0.008085307034013774, "test_return": 0.004742638606889072, "train_count": 129, "val_count": 58, "test_count": 42, "train_win_rate": 0.5426356589147286, "val_win_rate": 0.6551724137931034, "test_win_rate": 0.6666666666666666, "roe": 6.36, "revenue_growth": 1.8, "profit_growth": 1.9, "gross_margin": null, "debt_ratio": 91.67}, {"symbol": "sz002404", "train_return": 0.0019383767655443216, "val_return": 0.01977174893953271, "test_return": 0.004727716167931478, "train_count": 110, "val_count": 49, "test_count": 31, "train_win_rate": 0.5454545454545454, "val_win_rate": 0.7142857142857143, "test_win_rate": 0.4838709677419355, "roe": 7.7, "revenue_growth": 0.78, "profit_growth": 0.19, "gross_margin": 12.18, "debt_ratio": 41.5}, {"symbol": "sz300514", "train_return": 0.002440770610551713, "val_return": 0.003462521782720427, "test_return": 0.004484487462749869, "train_count": 135, "val_count": 38, "test_count": 27, "train_win_rate": 0.4888888888888889, "val_win_rate": 0.5526315789473685, "test_win_rate": 0.5185185185185185, "roe": 6.96, "revenue_growth": -29.01, "profit_growth": -52.81, "gross_margin": 38.31, "debt_ratio": 27.68}, {"symbol": "sz300690", "train_return": 0.015489033253190853, "val_return": 0.059271208423508456, "test_return": 0.004474499197605496, "train_count": 79, "val_count": 39, "test_count": 46, "train_win_rate": 0.5063291139240507, "val_win_rate": 0.6153846153846154, "test_win_rate": 0.41304347826086957, "roe": 9.36, "revenue_growth": 15.41, "profit_growth": 125.25, "gross_margin": 27.23, "debt_ratio": 18.59}, {"symbol": "sh688025", "train_return": 0.01813130840479807, "val_return": 0.0031635092050548903, "test_return": 0.004365781569660988, "train_count": 102, "val_count": 40, "test_count": 33, "train_win_rate": 0.5294117647058824, "val_win_rate": 0.4, "test_win_rate": 0.36363636363636365, "roe": 9.66, "revenue_growth": 41.02, "profit_growth": 97.3, "gross_margin": 40.58, "debt_ratio": 29.18}, {"symbol": "sz301259", "train_return": 0.011803448075734267, "val_return": 0.027682349049250096, "test_return": 0.004360692658251751, "train_count": 35, "val_count": 52, "test_count": 29, "train_win_rate": 0.5428571428571428, "val_win_rate": 0.5769230769230769, "test_win_rate": 0.3793103448275862, "roe": -0.89, "revenue_growth": 74.38, "profit_growth": 77.94, "gross_margin": 28.64, "debt_ratio": 42.64}, {"symbol": "sz000868", "train_return": 0.0033612094492516116, "val_return": 0.019572444866659103, "test_return": 0.004318401846840463, "train_count": 124, "val_count": 36, "test_count": 21, "train_win_rate": 0.4435483870967742, "val_win_rate": 0.6388888888888888, "test_win_rate": 0.5238095238095238, "roe": -1.01, "revenue_growth": 44.37, "profit_growth": -61.56, "gross_margin": 8.01, "debt_ratio": 79.15}, {"symbol": "sz300953", "train_return": 0.008965962206929398, "val_return": 0.04147844952183093, "test_return": 0.004223654956304603, "train_count": 77, "val_count": 48, "test_count": 33, "train_win_rate": 0.44155844155844154, "val_win_rate": 0.6875, "test_win_rate": 0.42424242424242425, "roe": 11.38, "revenue_growth": 31.47, "profit_growth": 138.93, "gross_margin": 15.71, "debt_ratio": 64.43}, {"symbol": "sz002932", "train_return": 0.014195770325457328, "val_return": 0.00661585287487711, "test_return": 0.004008230535835436, "train_count": 65, "val_count": 52, "test_count": 41, "train_win_rate": 0.4461538461538462, "val_win_rate": 0.5576923076923077, "test_win_rate": 0.5609756097560976, "roe": 0.24, "revenue_growth": 0.53, "profit_growth": -83.3, "gross_margin": 32.31, "debt_ratio": 6.13}, {"symbol": "sh601628", "train_return": 0.005875467840265749, "val_return": 0.015916847401405376, "test_return": 0.00392830214069284, "train_count": 82, "val_count": 25, "test_count": 53, "train_win_rate": 0.5365853658536586, "val_win_rate": 0.64, "test_win_rate": 0.5660377358490566, "roe": 29.27, "revenue_growth": 25.92, "profit_growth": 60.54, "gross_margin": null, "debt_ratio": 91.39}, {"symbol": "sz300192", "train_return": 0.0074085740307736426, "val_return": 0.013169790730227783, "test_return": 0.0039178534924957835, "train_count": 102, "val_count": 48, "test_count": 24, "train_win_rate": 0.5, "val_win_rate": 0.4583333333333333, "test_win_rate": 0.5, "roe": 9.41, "revenue_growth": -3.64, "profit_growth": -12.98, "gross_margin": 35.99, "debt_ratio": 25.19}, {"symbol": "sh601368", "train_return": 0.003628183041477544, "val_return": 0.005394695606340034, "test_return": 0.0036237889701111192, "train_count": 84, "val_count": 42, "test_count": 33, "train_win_rate": 0.5595238095238095, "val_win_rate": 0.5952380952380952, "test_win_rate": 0.5454545454545454, "roe": 2.82, "revenue_growth": 1.3, "profit_growth": 0.97, "gross_margin": 40.06, "debt_ratio": 80.29}, {"symbol": "sz002386", "train_return": 0.016374537601806877, "val_return": 0.001041707190982324, "test_return": 0.003622638373259876, "train_count": 57, "val_count": 55, "test_count": 42, "train_win_rate": 0.43859649122807015, "val_win_rate": 0.5818181818181818, "test_win_rate": 0.5714285714285714, "roe": 0.42, "revenue_growth": -14.89, "profit_growth": 132.63, "gross_margin": 7.24, "debt_ratio": 60.37}, {"symbol": "sz300473", "train_return": 0.0116958810897849, "val_return": 0.002482689446412699, "test_return": 0.003619856893565902, "train_count": 88, "val_count": 46, "test_count": 38, "train_win_rate": 0.5340909090909091, "val_win_rate": 0.41304347826086957, "test_win_rate": 0.47368421052631576, "roe": 4.87, "revenue_growth": 7.67, "profit_growth": 228.13, "gross_margin": 19.22, "debt_ratio": 58.72}, {"symbol": "sz301033", "train_return": 0.0017259448466930302, "val_return": 0.01480177329522912, "test_return": 0.003540852002721251, "train_count": 57, "val_count": 59, "test_count": 39, "train_win_rate": 0.43859649122807015, "val_win_rate": 0.559322033898305, "test_win_rate": 0.46153846153846156, "roe": 10.43, "revenue_growth": 30.53, "profit_growth": 43.65, "gross_margin": 80.87, "debt_ratio": 11.04}, {"symbol": "sh600461", "train_return": 0.011783000394194278, "val_return": 0.004091434546398316, "test_return": 0.0035214776287861515, "train_count": 117, "val_count": 54, "test_count": 34, "train_win_rate": 0.5982905982905983, "val_win_rate": 0.48148148148148145, "test_win_rate": 0.47058823529411764, "roe": 9.72, "revenue_growth": -3.85, "profit_growth": 1.18, "gross_margin": 34.88, "debt_ratio": 56.37}, {"symbol": "sh601139", "train_return": 0.017234308955564645, "val_return": 0.005676313386913613, "test_return": 0.003337571403740394, "train_count": 75, "val_count": 37, "test_count": 31, "train_win_rate": 0.6133333333333333, "val_win_rate": 0.5405405405405406, "test_win_rate": 0.5806451612903226, "roe": 5.78, "revenue_growth": 8.63, "profit_growth": -13.08, "gross_margin": 15.4, "debt_ratio": 59.94}, {"symbol": "sz002701", "train_return": 0.0037564675953743495, "val_return": 0.008050695595405829, "test_return": 0.0032708357817794673, "train_count": 92, "val_count": 60, "test_count": 28, "train_win_rate": 0.41304347826086957, "val_win_rate": 0.5666666666666667, "test_win_rate": 0.6428571428571429, "roe": 11.38, "revenue_growth": 68.97, "profit_growth": 41.4, "gross_margin": 13.52, "debt_ratio": 65.67}, {"symbol": "sz002239", "train_return": 0.01765270341971016, "val_return": 0.006937896906887629, "test_return": 0.0032590230971371033, "train_count": 87, "val_count": 33, "test_count": 26, "train_win_rate": 0.4827586206896552, "val_win_rate": 0.3939393939393939, "test_win_rate": 0.34615384615384615, "roe": 2.02, "revenue_growth": 6.5, "profit_growth": 22.46, "gross_margin": 12.73, "debt_ratio": 49.2}, {"symbol": "sz920207", "train_return": 0.03314293278416102, "val_return": 0.012769763577696512, "test_return": 0.0030907907234996356, "train_count": 31, "val_count": 47, "test_count": 46, "train_win_rate": 0.3225806451612903, "val_win_rate": 0.40425531914893614, "test_win_rate": 0.45652173913043476, "roe": -3.37, "revenue_growth": -1.09, "profit_growth": 64.32, "gross_margin": 22.59, "debt_ratio": 59.24}, {"symbol": "sh600558", "train_return": 0.0009749303874772762, "val_return": 0.008102340267320696, "test_return": 0.002945119121474385, "train_count": 154, "val_count": 64, "test_count": 57, "train_win_rate": 0.5, "val_win_rate": 0.625, "test_win_rate": 0.5087719298245614, "roe": 5.95, "revenue_growth": 4.55, "profit_growth": 64.77, "gross_margin": 16.42, "debt_ratio": 19.93}, {"symbol": "sz002188", "train_return": 0.0060967494559890315, "val_return": 0.009979988342201556, "test_return": 0.002889679787279316, "train_count": 120, "val_count": 58, "test_count": 42, "train_win_rate": 0.425, "val_win_rate": 0.6379310344827587, "test_win_rate": 0.5952380952380952, "roe": 7.17, "revenue_growth": 12.89, "profit_growth": 642.28, "gross_margin": 22.21, "debt_ratio": 37.73}, {"symbol": "sh600724", "train_return": 0.012551744544766666, "val_return": 0.0020024898758578234, "test_return": 0.002794400124099296, "train_count": 100, "val_count": 32, "test_count": 31, "train_win_rate": 0.48, "val_win_rate": 0.4375, "test_win_rate": 0.5806451612903226, "roe": 5.82, "revenue_growth": -11.44, "profit_growth": 5.63, "gross_margin": 28.67, "debt_ratio": 21.14}, {"symbol": "sh603203", "train_return": 0.008964392408316259, "val_return": 0.005909065740459978, "test_return": 0.002500802115569736, "train_count": 87, "val_count": 64, "test_count": 52, "train_win_rate": 0.5172413793103449, "val_win_rate": 0.4375, "test_win_rate": 0.4807692307692308, "roe": 13.1, "revenue_growth": 18.3, "profit_growth": 21.83, "gross_margin": 49.45, "debt_ratio": 31.12}, {"symbol": "sz920429", "train_return": 0.05218921260784129, "val_return": 0.043250809868508946, "test_return": 0.002442230197132991, "train_count": 27, "val_count": 44, "test_count": 34, "train_win_rate": 0.7407407407407407, "val_win_rate": 0.6590909090909091, "test_win_rate": 0.47058823529411764, "roe": 1.7, "revenue_growth": 4.16, "profit_growth": -77.73, "gross_margin": 32.56, "debt_ratio": 33.23}, {"symbol": "sz300424", "train_return": 0.009052863446163784, "val_return": 0.054234661638150175, "test_return": 0.002134557116268491, "train_count": 112, "val_count": 42, "test_count": 43, "train_win_rate": 0.5267857142857143, "val_win_rate": 0.6190476190476191, "test_win_rate": 0.5348837209302325, "roe": 2.0, "revenue_growth": 2.77, "profit_growth": -7.31, "gross_margin": 28.86, "debt_ratio": 67.86}, {"symbol": "sh600725", "train_return": 0.005561266223456837, "val_return": 0.0012955172131194753, "test_return": 0.002087139241321658, "train_count": 104, "val_count": 48, "test_count": 32, "train_win_rate": 0.4807692307692308, "val_win_rate": 0.4791666666666667, "test_win_rate": 0.5625, "roe": -5.99, "revenue_growth": -19.62, "profit_growth": -90.01, "gross_margin": 1.1, "debt_ratio": 18.87}, {"symbol": "sz002955", "train_return": 0.017996061363423202, "val_return": 0.0032453650967313417, "test_return": 0.0020553984891155384, "train_count": 110, "val_count": 41, "test_count": 43, "train_win_rate": 0.509090909090909, "val_win_rate": 0.4634146341463415, "test_win_rate": 0.3953488372093023, "roe": 1.56, "revenue_growth": -8.13, "profit_growth": -76.67, "gross_margin": 24.54, "debt_ratio": 25.38}, {"symbol": "sz000719", "train_return": 0.010825219913667502, "val_return": 0.013097293794825254, "test_return": 0.0019144371509496121, "train_count": 104, "val_count": 50, "test_count": 50, "train_win_rate": 0.5288461538461539, "val_win_rate": 0.62, "test_win_rate": 0.48, "roe": 6.46, "revenue_growth": -1.17, "profit_growth": 46.94, "gross_margin": 37.71, "debt_ratio": 38.14}, {"symbol": "sh603519", "train_return": 0.00667599920653296, "val_return": 0.035505078254525195, "test_return": 0.001909556298598467, "train_count": 108, "val_count": 22, "test_count": 34, "train_win_rate": 0.5092592592592593, "val_win_rate": 0.7727272727272727, "test_win_rate": 0.5588235294117647, "roe": 9.26, "revenue_growth": 0.24, "profit_growth": 7.16, "gross_margin": 16.17, "debt_ratio": 23.92}, {"symbol": "sh603800", "train_return": 0.010255557605105716, "val_return": 0.022224537963845332, "test_return": 0.0018739899385077574, "train_count": 131, "val_count": 53, "test_count": 46, "train_win_rate": 0.5267175572519084, "val_win_rate": 0.5283018867924528, "test_win_rate": 0.4782608695652174, "roe": 7.46, "revenue_growth": -16.99, "profit_growth": -26.66, "gross_margin": 25.17, "debt_ratio": 62.79}, {"symbol": "sh600675", "train_return": 0.019038690818513476, "val_return": 0.02849908203441176, "test_return": 0.0018277976763518104, "train_count": 81, "val_count": 44, "test_count": 18, "train_win_rate": 0.5061728395061729, "val_win_rate": 0.5681818181818182, "test_win_rate": 0.3888888888888889, "roe": 2.42, "revenue_growth": 336.81, "profit_growth": 166.74, "gross_margin": 31.64, "debt_ratio": 66.03}, {"symbol": "sh601952", "train_return": 0.0048928493063615415, "val_return": 0.0018025764644051517, "test_return": 0.001717007706984134, "train_count": 89, "val_count": 41, "test_count": 24, "train_win_rate": 0.5168539325842697, "val_win_rate": 0.4634146341463415, "test_win_rate": 0.375, "roe": 4.42, "revenue_growth": -8.63, "profit_growth": -33.37, "gross_margin": 12.32, "debt_ratio": 51.41}, {"symbol": "sz001278", "train_return": 0.0036419304665929516, "val_return": 0.00791160403640867, "test_return": 0.0015288482472181981, "train_count": 37, "val_count": 44, "test_count": 39, "train_win_rate": 0.43243243243243246, "val_win_rate": 0.45454545454545453, "test_win_rate": 0.5897435897435898, "roe": -2.92, "revenue_growth": -1.24, "profit_growth": -186.34, "gross_margin": 14.14, "debt_ratio": 67.37}, {"symbol": "sh688358", "train_return": 0.004446130576541027, "val_return": 0.015417508751156777, "test_return": 0.0014047532444663297, "train_count": 71, "val_count": 48, "test_count": 21, "train_win_rate": 0.352112676056338, "val_win_rate": 0.5208333333333334, "test_win_rate": 0.42857142857142855, "roe": 6.63, "revenue_growth": -5.27, "profit_growth": -4.56, "gross_margin": 59.82, "debt_ratio": 11.24}, {"symbol": "sz300332", "train_return": 0.029781756174850987, "val_return": 0.02369963586376807, "test_return": 0.001254172018902554, "train_count": 77, "val_count": 24, "test_count": 43, "train_win_rate": 0.6103896103896104, "val_win_rate": 0.4166666666666667, "test_win_rate": 0.5116279069767442, "roe": 2.24, "revenue_growth": -36.05, "profit_growth": -27.25, "gross_margin": 16.9, "debt_ratio": 43.27}, {"symbol": "sz002204", "train_return": 0.004558174838422152, "val_return": 0.012934372466453025, "test_return": 0.0011988419613940464, "train_count": 69, "val_count": 33, "test_count": 38, "train_win_rate": 0.4057971014492754, "val_win_rate": 0.5454545454545454, "test_win_rate": 0.39473684210526316, "roe": 6.5, "revenue_growth": 8.11, "profit_growth": 23.97, "gross_margin": 18.95, "debt_ratio": 70.96}, {"symbol": "sz301127", "train_return": 0.005993051617681924, "val_return": 0.03522323227921292, "test_return": 0.001123136536661934, "train_count": 37, "val_count": 31, "test_count": 38, "train_win_rate": 0.6486486486486487, "val_win_rate": 0.7741935483870968, "test_win_rate": 0.5263157894736842, "roe": 4.13, "revenue_growth": -5.21, "profit_growth": -26.48, "gross_margin": 34.35, "debt_ratio": 61.79}, {"symbol": "sh603819", "train_return": 0.002935515395681251, "val_return": 0.016501460848672007, "test_return": 0.0009352492700319395, "train_count": 63, "val_count": 31, "test_count": 39, "train_win_rate": 0.4603174603174603, "val_win_rate": 0.6129032258064516, "test_win_rate": 0.6153846153846154, "roe": 2.15, "revenue_growth": 20.27, "profit_growth": 135.99, "gross_margin": 7.77, "debt_ratio": 49.17}, {"symbol": "sh603888", "train_return": 0.007339502105692499, "val_return": 0.007150597992863822, "test_return": 0.0007895101383606622, "train_count": 111, "val_count": 57, "test_count": 48, "train_win_rate": 0.5225225225225225, "val_win_rate": 0.5789473684210527, "test_win_rate": 0.5, "roe": 5.66, "revenue_growth": 7.88, "profit_growth": 30.56, "gross_margin": 38.37, "debt_ratio": 25.31}, {"symbol": "sh688292", "train_return": 0.0008974612701922021, "val_return": 1.3557321382722946e-05, "test_return": 0.00036711777915747755, "train_count": 33, "val_count": 29, "test_count": 45, "train_win_rate": 0.48484848484848486, "val_win_rate": 0.4482758620689655, "test_win_rate": 0.4666666666666667, "roe": -0.86, "revenue_growth": -21.51, "profit_growth": -124.88, "gross_margin": 58.51, "debt_ratio": 29.97}, {"symbol": "sz300798", "train_return": 0.007670835072849689, "val_return": 0.013449441240248052, "test_return": 0.00036313918602038503, "train_count": 91, "val_count": 32, "test_count": 32, "train_win_rate": 0.5274725274725275, "val_win_rate": 0.59375, "test_win_rate": 0.53125, "roe": -0.88, "revenue_growth": 23.49, "profit_growth": -272.46, "gross_margin": 12.84, "debt_ratio": 35.57}, {"symbol": "sh600215", "train_return": 0.02618558765589304, "val_return": 0.021662896096342688, "test_return": 0.00034501920134307574, "train_count": 81, "val_count": 43, "test_count": 43, "train_win_rate": 0.48148148148148145, "val_win_rate": 0.6511627906976745, "test_win_rate": 0.46511627906976744, "roe": -4.24, "revenue_growth": -52.31, "profit_growth": -198.57, "gross_margin": -1.4, "debt_ratio": 36.33}, {"symbol": "sz002893", "train_return": 0.018723373499322665, "val_return": 0.015860506082229085, "test_return": 0.0003061798016396307, "train_count": 89, "val_count": 57, "test_count": 53, "train_win_rate": 0.4606741573033708, "val_win_rate": 0.5964912280701754, "test_win_rate": 0.5094339622641509, "roe": 4.82, "revenue_growth": 24.03, "profit_growth": 35.57, "gross_margin": 23.34, "debt_ratio": 45.58}, {"symbol": "sz000410", "train_return": 0.0021922239878439413, "val_return": 0.0036316912734955667, "test_return": 0.00023260468318565697, "train_count": 113, "val_count": 34, "test_count": 34, "train_win_rate": 0.415929203539823, "val_win_rate": 0.47058823529411764, "test_win_rate": 0.5, "roe": 0.05, "revenue_growth": 0.44, "profit_growth": 101.67, "gross_margin": 14.48, "debt_ratio": 54.98}, {"symbol": "sh600281", "train_return": 0.009323117195541894, "val_return": 0.04216291587950519, "test_return": 0.00014815411813712078, "train_count": 98, "val_count": 42, "test_count": 37, "train_win_rate": 0.5408163265306123, "val_win_rate": 0.5714285714285714, "test_win_rate": 0.32432432432432434, "roe": 71.86, "revenue_growth": 31.1, "profit_growth": 178.58, "gross_margin": 3.68, "debt_ratio": 86.51}, {"symbol": "sz301361", "train_return": 0.04565857604106909, "val_return": 0.026397775783122704, "test_return": 0.00012142670473556286, "train_count": 54, "val_count": 51, "test_count": 49, "train_win_rate": 0.5, "val_win_rate": 0.4117647058823529, "test_win_rate": 0.46938775510204084, "roe": 5.99, "revenue_growth": 28.02, "profit_growth": 37.02, "gross_margin": 58.97, "debt_ratio": 4.51}, {"symbol": "sz002561", "train_return": 0.015583806660994329, "val_return": 0.01932931982748107, "test_return": 8.292843132118207e-05, "train_count": 82, "val_count": 37, "test_count": 27, "train_win_rate": 0.4878048780487805, "val_win_rate": 0.5675675675675675, "test_win_rate": 0.48148148148148145, "roe": -0.09, "revenue_growth": -16.92, "profit_growth": -5.87, "gross_margin": 58.14, "debt_ratio": 14.71}]